Workbook
Name SegmentaciónDeDatos_Clase_Del_Pasaje: #N/A
Name SegmentaciónDeDatos_Embarque: #N/A
Name SegmentaciónDeDatos_Sexo: #N/A

Sheet PORTADA
J1: Versión 1.0 — Marzo 2026
F2: ANÁLISIS DE SUPERVIVENCIA — TITANIC
F6: Trabájo Practico Final — Excel
F8: Matias Lieggi

Sheet README
A3: Dataset Extraído de Kaggle, con información sobre la tragedia del Titanic.
A4: 1.Se exporto el archivo CSV, a excel. Al copiar el dataset crudo, se utilizo la funcion Texto en columnas.
A5: 2.Al corroborar si había celdas vacías en cada columna, se detectó que las columnas Edad. Y Cabina tenian varios datos faltantes.
A6: 2.Para solucionar el error detectado en la columna Edad inserte una columna a la izquierda. Yutilice la formula : " =Si(ES.BLANCO(G2)ALEATORIO.ENTRE(1;80);G2) " y luego Copié y pegue los datos como Valor, para que no cambie constantemente dichos valores.
A7: 3.En el caso de la columna Cabina, habia muchisimos mas datos faltantes que en Edad. Y al tratarse de un dato distinto y mas complejo, Decidí utilizar la formula : " =SI(ESBLANCO(M2);"Desconocido";M2)) " insertando una columna a la izquierda y luego copiando los datos como valores
A8: 4.En el caso de la columna Fare, Precio: Tenia valores mixtos en formato Texto y Número. Siendo Precio de los pasajes, necesitamos el dato en Número. Entonces utilice la formula " =VALOR(SUSTITUIR;L2;".";",") " y asi logre tener todas las celdas con valor Número
A9: 5. En DATASET_CLEAN Re ordené las columnas de manera coherente. Y Reformulé los titulos de dichas columnas con los nombres al español.
A10: 6.Aplique Validación de datos en la columna Sexo y Embarque. En Sexo utilice como validación de datos tipo " Lista "y que los generos sean male ; female ( hombre ; mujer). En embarque también aplique formato Lista y que las opciones sean " S;C;Q "
A11: 7.Para la primer pregunta Calculé cantidades de pasarejos clasificados en " male " (hombres) y "female" (mujeres) utilizando Formula "=CONTAR.SI " luego calcule el porcentaje de hombres y mujeres sobre el total de pasarejos, utilizando CONTAR.SI / CONTARA y REDONDEAR.MAS REDONDEAR.MENOS
A12: 8.Me pregunté si existian diferencias entre la edad de pasarejos que sobrevivieron y los que no. Increiblemente la diferencia en promedio de edad de cada uno es minima. Y es por ello me abrió la incertidumbre a generar otra pregunta.
A13: 9. Dicha pregunta fue saber la tasa de supervivencia, de cada grupo etario: ( Niños, Jóvenes, Adultos y Adultos mayores). Al obtener estos datos utilizando formula " = CONTAR.SI.CONJUNTO" luego pude identificar y sacar una conclusión.
A14: 10. La conclusión que pude sacar es que los adultos mayores con la tasa menor de supervivencia(31%), Y los Jóvenes (35%) Me dieron a entender que claramente, El enfoque estaba en que los niños fueran quienes debían sobrevivir por encima del resto, Mientras que los grupos de mayor edad tenían menos prioridad en la evacuación
... A44: Asimismo las diferencias en las tarifas reflejan una marcada desiguladad socioeconomica entre clases, l ocual se vincula con las distintas tasas de supervivencia observadas. En conjunto, los datos evidencian que factores estructurales y sociales tuvieron peso determinante en los resultados.

Sheet DATASET_ORIGINAL
A3: PassengerId,Survived,Pclass,Name,Sex,Age,SibSp,Parch,Ticket,Fare,Cabin,Embarked
A4: 1,0,3,"Braund, Mr. Owen Harris",male,22,1,0,A/5 21171,7.25,,S
A5: 2,1,1,"Cumings, Mrs. John Bradley (Florence Briggs Thayer)",female,38,1,0,PC 17599,71.2833,C85,C
A6: 3,1,3,"Heikkinen, Miss. Laina",female,26,0,0,STON/O2. 3101282,7.925,,S
A7: 4,1,1,"Futrelle, Mrs. Jacques Heath (Lily May Peel)",female,35,1,0,113803,53.1,C123,S
A8: 5,0,3,"Allen, Mr. William Henry",male,35,0,0,373450,8.05,,S
A9: 6,0,3,"Moran, Mr. James",male,,0,0,330877,8.4583,,Q
A10: 7,0,1,"McCarthy, Mr. Timothy J",male,54,0,0,17463,51.8625,E46,S
A11: 8,0,3,"Palsson, Master. Gosta Leonard",male,2,3,1,349909,21.075,,S
A12: 9,1,3,"Johnson, Mrs. Oscar W (Elisabeth Vilhelmina Berg)",female,27,0,2,347742,11.1333,,S
A13: 10,1,2,"Nasser, Mrs. Nicholas (Adele Achem)",female,14,1,0,237736,30.0708,,C
A14: 11,1,3,"Sandstrom, Miss. Marguerite Rut",female,4,1,1,PP 9549,16.7,G6,S
... A894: 891,0,3,"Dooley, Mr. Patrick",male,32,0,0,370376,7.75,,Q

Sheet DATASET
A3: PassengerId. | B3: Survived | C3: Pclass | D3: Name . | E3: Sex . | F3: Age Clean | G3: Age Correción 2 | H3: Age Correción. | I3: Age | J3: SibSp | K3: Parch | L3: Ticket | M3: Fare correción | N3: Fare | O3: Cabin Correción | P3: Cabin | Q3: Embarked
A4: 546 | B4: 0 | C4: 1 | D4: Nicholson, Mr. Arthur Ernest | E4: male | F4: =ROUNDUP(Titanic_DATASET[[#This Row],[Age Correción 2]],0) -> 64 | G4: =VALUE(SUBSTITUTE(Titanic_DATASET[[#This Row],[Age Correción.]],".",",")) -> 64 | H4: 64 | I4: 64 | J4: 0 | K4: 0 | L4: 693 | M4: =VALUE(SUBSTITUTE(N4,".",",")) -> 26 | N4: 26 | O4: =IF(ISBLANK(P4),"Desconocido",P4) -> Desconocido | Q4: S
A5: 873 | B5: 0 | C5: 1 | D5: Carlsson, Mr. Frans Olof | E5: male | F5: =ROUNDUP(Titanic_DATASET[[#This Row],[Age Correción 2]],0) -> 33 | G5: =VALUE(SUBSTITUTE(Titanic_DATASET[[#This Row],[Age Correción.]],".",",")) -> 33 | H5: 33 | I5: 33 | J5: 0 | K5: 0 | L5: 695 | M5: =VALUE(SUBSTITUTE(N5,".",",")) -> 5 | N5: 5 | O5: =IF(ISBLANK(P5),"Desconocido",P5) -> B51 B53 B55 | P5: B51 B53 B55 | Q5: S
A6: 75 | B6: 1 | C6: 3 | D6: Bing, Mr. Lee | E6: male | F6: =ROUNDUP(Titanic_DATASET[[#This Row],[Age Correción 2]],0) -> 32 | G6: =VALUE(SUBSTITUTE(Titanic_DATASET[[#This Row],[Age Correción.]],".",",")) -> 32 | H6: 32 | I6: 32 | J6: 0 | K6: 0 | L6: 1601 | M6: =VALUE(SUBSTITUTE(N6,".",",")) -> 564958 | N6: 564958 | O6: =IF(ISBLANK(P6),"Desconocido",P6) -> Desconocido | Q6: S
A7: 170 | B7: 0 | C7: 3 | D7: Ling, Mr. Lee | E7: male | F7: =ROUNDUP(Titanic_DATASET[[#This Row],[Age Correción 2]],0) -> 28 | G7: =VALUE(SUBSTITUTE(Titanic_DATASET[[#This Row],[Age Correción.]],".",",")) -> 28 | H7: 28 | I7: 28 | J7: 0 | K7: 0 | L7: 1601 | M7: =VALUE(SUBSTITUTE(N7,".",",")) -> 564958 | N7: 564958 | O7: =IF(ISBLANK(P7),"Desconocido",P7) -> Desconocido | Q7: S
A8: 510 | B8: 1 | C8: 3 | D8: Lang, Mr. Fang | E8: male | F8: =ROUNDUP(Titanic_DATASET[[#This Row],[Age Correción 2]],0) -> 26 | G8: =VALUE(SUBSTITUTE(Titanic_DATASET[[#This Row],[Age Correción.]],".",",")) -> 26 | H8: 26 | I8: 26 | J8: 0 | K8: 0 | L8: 1601 | M8: =VALUE(SUBSTITUTE(N8,".",",")) -> 564958 | N8: 564958 | O8: =IF(ISBLANK(P8),"Desconocido",P8) -> Desconocido | Q8: S
A9: 644 | B9: 1 | C9: 3 | D9: Foo, Mr. Choong | E9: male | F9: =ROUNDUP(Titanic_DATASET[[#This Row],[Age Correción 2]],0) -> 42 | G9: =VALUE(SUBSTITUTE(Titanic_DATASET[[#This Row],[Age Correción.]],".",",")) -> 42 | H9: 42 | J9: 0 | K9: 0 | L9: 1601 | M9: =VALUE(SUBSTITUTE(N9,".",",")) -> 564958 | N9: 564958 | O9: =IF(ISBLANK(P9),"Desconocido",P9) -> Desconocido | Q9: S
A10: 693 | B10: 1 | C10: 3 | D10: Lam, Mr. Ali | E10: male | F10: =ROUNDUP(Titanic_DATASET[[#This Row],[Age Correción 2]],0) -> 58 | G10: =VALUE(SUBSTITUTE(Titanic_DATASET[[#This Row],[Age Correción.]],".",",")) -> 58 | H10: 58 | J10: 0 | K10: 0 | L10: 1601 | M10: =VALUE(SUBSTITUTE(N10,".",",")) -> 564958 | N10: 564958 | O10: =IF(ISBLANK(P10),"Desconocido",P10) -> Desconocido | Q10: S
A11: 827 | B11: 0 | C11: 3 | D11: Lam, Mr. Len | E11: male | F11: =ROUNDUP(Titanic_DATASET[[#This Row],[Age Correción 2]],0) -> 57 | G11: =VALUE(SUBSTITUTE(Titanic_DATASET[[#This Row],[Age Correción.]],".",",")) -> 57 | H11: 57 | J11: 0 | K11: 0 | L11: 1601 | M11: =VALUE(SUBSTITUTE(N11,".",",")) -> 564958 | N11: 564958 | O11: =IF(ISBLANK(P11),"Desconocido",P11) -> Desconocido | Q11: S
A12: 839 | B12: 1 | C12: 3 | D12: Chip, Mr. Chang | E12: male | F12: =ROUNDUP(Titanic_DATASET[[#This Row],[Age Correción 2]],0) -> 32 | G12: =VALUE(SUBSTITUTE(Titanic_DATASET[[#This Row],[Age Correción.]],".",",")) -> 32 | H12: 32 | I12: 32 | J12: 0 | K12: 0 | L12: 1601 | M12: =VALUE(SUBSTITUTE(N12,".",",")) -> 564958 | N12: 564958 | O12: =IF(ISBLANK(P12),"Desconocido",P12) -> Desconocido | Q12: S
A13: 427 | B13: 1 | C13: 2 | D13: Clarke, Mrs. Charles V (Ada Maria Winfield) | E13: female | F13: =ROUNDUP(Titanic_DATASET[[#This Row],[Age Correción 2]],0) -> 28 | G13: =VALUE(SUBSTITUTE(Titanic_DATASET[[#This Row],[Age Correción.]],".",",")) -> 28 | H13: 28 | I13: 28 | J13: 1 | K13: 0 | L13: 2003 | M13: =VALUE(SUBSTITUTE(N13,".",",")) -> 26 | N13: 26 | O13: =IF(ISBLANK(P13),"Desconocido",P13) -> Desconocido | Q13: S
A14: 835 | B14: 0 | C14: 3 | D14: Allum, Mr. Owen George | E14: male | F14: =ROUNDUP(Titanic_DATASET[[#This Row],[Age Correción 2]],0) -> 18 | G14: =VALUE(SUBSTITUTE(Titanic_DATASET[[#This Row],[Age Correción.]],".",",")) -> 18 | H14: 18 | I14: 18 | J14: 0 | K14: 0 | L14: 2223 | M14: =VALUE(SUBSTITUTE(N14,".",",")) -> 8.3 | N14: 8.3 | O14: =IF(ISBLANK(P14),"Desconocido",P14) -> Desconocido | Q14: S
A15: 554 | B15: 1 | C15: 3 | D15: Leeni, Mr. Fahim ("Philip Zenni") | E15: male | F15: =ROUNDUP(Titanic_DATASET[[#This Row],[Age Correción 2]],0) -> 22 | G15: =VALUE(SUBSTITUTE(Titanic_DATASET[[#This Row],[Age Correción.]],".",",")) -> 22 | H15: 22 | I15: 22 | J15: 0 | K15: 0 | L15: 2620 | M15: =VALUE(SUBSTITUTE(N15,".",",")) -> 7225 | N15: 7225 | O15: =IF(ISBLANK(P15),"Desconocido",P15) -> Desconocido | Q15: C
A16: 662 | B16: 0 | C16: 3 | D16: Badt, Mr. Mohamed | E16: male | F16: =ROUNDUP(Titanic_DATASET[[#This Row],[Age Correción 2]],0) -> 40 | G16: =VALUE(SUBSTITUTE(Titanic_DATASET[[#This Row],[Age Correción.]],".",",")) -> 40 | H16: 40 | I16: 40 | J16: 0 | K16: 0 | L16: 2623 | M16: =VALUE(SUBSTITUTE(N16,".",",")) -> 7225 | N16: 7225 | O16: =IF(ISBLANK(P16),"Desconocido",P16) -> Desconocido | Q16: C
A17: 523 | B17: 0 | C17: 3 | D17: Lahoud, Mr. Sarkis | E17: male | F17: =ROUNDUP(Titanic_DATASET[[#This Row],[Age Correción 2]],0) -> 59 | G17: =VALUE(SUBSTITUTE(Titanic_DATASET[[#This Row],[Age Correción.]],".",",")) -> 59 | H17: 59 | J17: 0 | K17: 0 | L17: 2624 | M17: =VALUE(SUBSTITUTE(N17,".",",")) -> 7225 | N17: 7225 | O17: =IF(ISBLANK(P17),"Desconocido",P17) -> Desconocido | Q17: C
A18: 804 | B18: 1 | C18: 3 | D18: Thomas, Master. Assad Alexander | E18: male | F18: =ROUNDUP(Titanic_DATASET[[#This Row],[Age Correción 2]],0) -> 1 | G18: =VALUE(SUBSTITUTE(Titanic_DATASET[[#This Row],[Age Correción.]],".",",")) -> 0.42 | H18: 0.42 | I18: 0.42 | J18: 0 | K18: 1 | L18: 2625 | M18: =VALUE(SUBSTITUTE(N18,".",",")) -> 85167 | N18: 85167 | O18: =IF(ISBLANK(P18),"Desconocido",P18) -> Desconocido | Q18: C
A19: 368 | B19: 1 | C19: 3 | D19: Moussa, Mrs. (Mantoura Boulos) | E19: female | F19: =ROUNDUP(Titanic_DATASET[[#This Row],[Age Correción 2]],0) -> 45 | G19: =VALUE(SUBSTITUTE(Titanic_DATASET[[#This Row],[Age Correción.]],".",",")) -> 45 | H19: 45 | J19: 0 | K19: 0 | L19: 2626 | M19: =VALUE(SUBSTITUTE(N19,".",",")) -> 72292 | N19: 72292 | O19: =IF(ISBLANK(P19),"Desconocido",P19) -> Desconocido | Q19: C
A20: 115 | B20: 0 | C20: 3 | D20: Attalah, Miss. Malake | E20: female | F20: =ROUNDUP(Titanic_DATASET[[#This Row],[Age Correción 2]],0) -> 17 | G20: =VALUE(SUBSTITUTE(Titanic_DATASET[[#This Row],[Age Correción.]],".",",")) -> 17 | H20: 17 | I20: 17 | J20: 0 | K20: 0 | L20: 2627 | M20: =VALUE(SUBSTITUTE(N20,".",",")) -> 144583 | N20: 144583 | O20: =IF(ISBLANK(P20),"Desconocido",P20) -> Desconocido | Q20: C
A21: 496 | B21: 0 | C21: 3 | D21: Yousseff, Mr. Gerious | E21: male | F21: =ROUNDUP(Titanic_DATASET[[#This Row],[Age Correción 2]],0) -> 80 | G21: =VALUE(SUBSTITUTE(Titanic_DATASET[[#This Row],[Age Correción.]],".",",")) -> 80 | H21: 80 | J21: 0 | K21: 0 | L21: 2627 | M21: =VALUE(SUBSTITUTE(N21,".",",")) -> 144583 | N21: 144583 | O21: =IF(ISBLANK(P21),"Desconocido",P21) -> Desconocido | Q21: C
A22: 204 | B22: 0 | C22: 3 | D22: Youseff, Mr. Gerious | E22: male | F22: =ROUNDUP(Titanic_DATASET[[#This Row],[Age Correción 2]],0) -> 46 | G22: =VALUE(SUBSTITUTE(Titanic_DATASET[[#This Row],[Age Correción.]],".",",")) -> 45.5 | H22: 45.5 | I22: 45.5 | J22: 0 | K22: 0 | L22: 2628 | M22: =VALUE(SUBSTITUTE(N22,".",",")) -> 7225 | N22: 7225 | O22: =IF(ISBLANK(P22),"Desconocido",P22) -> Desconocido | Q22: C
A23: 860 | B23: 0 | C23: 3 | D23: Razi, Mr. Raihed | E23: male | F23: =ROUNDUP(Titanic_DATASET[[#This Row],[Age Correción 2]],0) -> 33 | G23: =VALUE(SUBSTITUTE(Titanic_DATASET[[#This Row],[Age Correción.]],".",",")) -> 33 | H23: 33 | J23: 0 | K23: 0 | L23: 2629 | M23: =VALUE(SUBSTITUTE(N23,".",",")) -> 72292 | N23: 72292 | O23: =IF(ISBLANK(P23),"Desconocido",P23) -> Desconocido | Q23: C
A24: 27 | B24: 0 | C24: 3 | D24: Emir, Mr. Farred Chehab | E24: male | F24: =ROUNDUP(Titanic_DATASET[[#This Row],[Age Correción 2]],0) -> 75 | G24: =VALUE(SUBSTITUTE(Titanic_DATASET[[#This Row],[Age Correción.]],".",",")) -> 75 | H24: 75 | J24: 0 | K24: 0 | L24: 2631 | M24: =VALUE(SUBSTITUTE(N24,".",",")) -> 7225 | N24: 7225 | O24: =IF(ISBLANK(P24),"Desconocido",P24) -> Desconocido | Q24: C
A25: 532 | B25: 0 | C25: 3 | D25: Toufik, Mr. Nakli | E25: male | F25: =ROUNDUP(Titanic_DATASET[[#This Row],[Age Correción 2]],0) -> 52 | G25: =VALUE(SUBSTITUTE(Titanic_DATASET[[#This Row],[Age Correción.]],".",",")) -> 52 | H25: 52 | J25: 0 | K25: 0 | L25: 2641 | M25: =VALUE(SUBSTITUTE(N25,".",",")) -> 72292 | N25: 72292 | O25: =IF(ISBLANK(P25),"Desconocido",P25) -> Desconocido | Q25: C
A26: 355 | B26: 0 | C26: 3 | D26: Yousif, Mr. Wazli | E26: male | F26: =ROUNDUP(Titanic_DATASET[[#This Row],[Age Correción 2]],0) -> 4 | G26: =VALUE(SUBSTITUTE(Titanic_DATASET[[#This Row],[Age Correción.]],".",",")) -> 4 | H26: 4 | J26: 0 | K26: 0 | L26: 2647 | M26: =VALUE(SUBSTITUTE(N26,".",",")) -> 7225 | N26: 7225 | O26: =IF(ISBLANK(P26),"Desconocido",P26) -> Desconocido | Q26: C
A27: 379 | B27: 0 | C27: 3 | D27: Betros, Mr. Tannous | E27: male | F27: =ROUNDUP(Titanic_DATASET[[#This Row],[Age Correción 2]],0) -> 20 | G27: =VALUE(SUBSTITUTE(Titanic_DATASET[[#This Row],[Age Correción.]],".",",")) -> 20 | H27: 20 | I27: 20 | J27: 0 | K27: 0 | L27: 2648 | M27: =VALUE(SUBSTITUTE(N27,".",",")) -> 40125 | N27: 40125 | O27: =IF(ISBLANK(P27),"Desconocido",P27) -> Desconocido | Q27: C
A28: 20 | B28: 1 | C28: 3 | D28: Masselmani, Mrs. Fatima | E28: female | F28: =ROUNDUP(Titanic_DATASET[[#This Row],[Age Correción 2]],0) -> 38 | G28: =VALUE(SUBSTITUTE(Titanic_DATASET[[#This Row],[Age Correción.]],".",",")) -> 38 | H28: 38 | J28: 0 | K28: 0 | L28: 2649 | M28: =VALUE(SUBSTITUTE(N28,".",",")) -> 7225 | N28: 7225 | O28: =IF(ISBLANK(P28),"Desconocido",P28) -> Desconocido | Q28: C
A29: 256 | B29: 1 | C29: 3 | D29: Touma, Mrs. Darwis (Hanne Youssef Razi) | E29: female | F29: =ROUNDUP(Titanic_DATASET[[#This Row],[Age Correción 2]],0) -> 29 | G29: =VALUE(SUBSTITUTE(Titanic_DATASET[[#This Row],[Age Correción.]],".",",")) -> 29 | H29: 29 | I29: 29 | J29: 0 | K29: 2 | L29: 2650 | M29: =VALUE(SUBSTITUTE(N29,".",",")) -> 152458 | N29: 152458 | O29: =IF(ISBLANK(P29),"Desconocido",P29) -> Desconocido | Q29: C
A30: 40 | B30: 1 | C30: 3 | D30: Nicola-Yarred, Miss. Jamila | E30: female | F30: =ROUNDUP(Titanic_DATASET[[#This Row],[Age Correción 2]],0) -> 14 | G30: =VALUE(SUBSTITUTE(Titanic_DATASET[[#This Row],[Age Correción.]],".",",")) -> 14 | H30: 14 | I30: 14 | J30: 1 | K30: 0 | L30: 2651 | M30: =VALUE(SUBSTITUTE(N30,".",",")) -> 112417 | N30: 112417 | O30: =IF(ISBLANK(P30),"Desconocido",P30) -> Desconocido | Q30: C
A31: 126 | B31: 1 | C31: 3 | D31: Nicola-Yarred, Master. Elias | E31: male | F31: =ROUNDUP(Titanic_DATASET[[#This Row],[Age Correción 2]],0) -> 12 | G31: =VALUE(SUBSTITUTE(Titanic_DATASET[[#This Row],[Age Correción.]],".",",")) -> 12 | H31: 12 | I31: 12 | J31: 1 | K31: 0 | L31: 2651 | M31: =VALUE(SUBSTITUTE(N31,".",",")) -> 112417 | N31: 112417 | O31: =IF(ISBLANK(P31),"Desconocido",P31) -> Desconocido | Q31: C
A32: 382 | B32: 1 | C32: 3 | D32: Nakid, Miss. Maria ("Mary") | E32: female | F32: =ROUNDUP(Titanic_DATASET[[#This Row],[Age Correción 2]],0) -> 1 | G32: =VALUE(SUBSTITUTE(Titanic_DATASET[[#This Row],[Age Correción.]],".",",")) -> 1 | H32: 1 | I32: 1 | J32: 0 | K32: 2 | L32: 2653 | M32: =VALUE(SUBSTITUTE(N32,".",",")) -> 157417 | N32: 157417 | O32: =IF(ISBLANK(P32),"Desconocido",P32) -> Desconocido | Q32: C
A33: 623 | B33: 1 | C33: 3 | D33: Nakid, Mr. Sahid | E33: male | F33: =ROUNDUP(Titanic_DATASET[[#This Row],[Age Correción 2]],0) -> 20 | G33: =VALUE(SUBSTITUTE(Titanic_DATASET[[#This Row],[Age Correción.]],".",",")) -> 20 | H33: 20 | I33: 20 | J33: 1 | K33: 1 | L33: 2653 | M33: =VALUE(SUBSTITUTE(N33,".",",")) -> 157417 | N33: 157417 | O33: =IF(ISBLANK(P33),"Desconocido",P33) -> Desconocido | Q33: C
A34: 621 | B34: 0 | C34: 3 | D34: Yasbeck, Mr. Antoni | E34: male | F34: =ROUNDUP(Titanic_DATASET[[#This Row],[Age Correción 2]],0) -> 27 | G34: =VALUE(SUBSTITUTE(Titanic_DATASET[[#This Row],[Age Correción.]],".",",")) -> 27 | H34: 27 | I34: 27 | J34: 1 | K34: 0 | L34: 2659 | M34: =VALUE(SUBSTITUTE(N34,".",",")) -> 144542 | N34: 144542 | O34: =IF(ISBLANK(P34),"Desconocido",P34) -> Desconocido | Q34: C
A35: 831 | B35: 1 | C35: 3 | D35: Yasbeck, Mrs. Antoni (Selini Alexander) | E35: female | F35: =ROUNDUP(Titanic_DATASET[[#This Row],[Age Correción 2]],0) -> 15 | G35: =VALUE(SUBSTITUTE(Titanic_DATASET[[#This Row],[Age Correción.]],".",",")) -> 15 | H35: 15 | I35: 15 | J35: 1 | K35: 0 | L35: 2659 | M35: =VALUE(SUBSTITUTE(N35,".",",")) -> 144542 | N35: 144542 | O35: =IF(ISBLANK(P35),"Desconocido",P35) -> Desconocido | Q35: C
A36: 66 | B36: 1 | C36: 3 | D36: Moubarek, Master. Gerios | E36: male | F36: =ROUNDUP(Titanic_DATASET[[#This Row],[Age Correción 2]],0) -> 38 | G36: =VALUE(SUBSTITUTE(Titanic_DATASET[[#This Row],[Age Correción.]],".",",")) -> 38 | H36: 38 | J36: 1 | K36: 1 | L36: 2661 | M36: =VALUE(SUBSTITUTE(N36,".",",")) -> 152458 | N36: 152458 | O36: =IF(ISBLANK(P36),"Desconocido",P36) -> Desconocido | Q36: C
A37: 710 | B37: 1 | C37: 3 | D37: Moubarek, Master. Halim Gonios ("William George") | E37: male | F37: =ROUNDUP(Titanic_DATASET[[#This Row],[Age Correción 2]],0) -> 36 | G37: =VALUE(SUBSTITUTE(Titanic_DATASET[[#This Row],[Age Correción.]],".",",")) -> 36 | H37: 36 | J37: 1 | K37: 1 | L37: 2661 | M37: =VALUE(SUBSTITUTE(N37,".",",")) -> 152458 | N37: 152458 | O37: =IF(ISBLANK(P37),"Desconocido",P37) -> Desconocido | Q37: C
A38: 49 | B38: 0 | C38: 3 | D38: Samaan, Mr. Youssef | E38: male | F38: =ROUNDUP(Titanic_DATASET[[#This Row],[Age Correción 2]],0) -> 78 | G38: =VALUE(SUBSTITUTE(Titanic_DATASET[[#This Row],[Age Correción.]],".",",")) -> 78 | H38: 78 | J38: 2 | K38: 0 | L38: 2662 | M38: =VALUE(SUBSTITUTE(N38,".",",")) -> 216792 | N38: 216792 | O38: =IF(ISBLANK(P38),"Desconocido",P38) -> Desconocido | Q38: C
A39: 763 | B39: 1 | C39: 3 | D39: Barah, Mr. Hanna Assi | E39: male | F39: =ROUNDUP(Titanic_DATASET[[#This Row],[Age Correción 2]],0) -> 20 | G39: =VALUE(SUBSTITUTE(Titanic_DATASET[[#This Row],[Age Correción.]],".",",")) -> 20 | H39: 20 | I39: 20 | J39: 0 | K39: 0 | L39: 2663 | M39: =VALUE(SUBSTITUTE(N39,".",",")) -> 72292 | N39: 72292 | O39: =IF(ISBLANK(P39),"Desconocido",P39) -> Desconocido | Q39: C
A40: 599 | B40: 0 | C40: 3 | D40: Boulos, Mr. Hanna | E40: male | F40: =ROUNDUP(Titanic_DATASET[[#This Row],[Age Correción 2]],0) -> 5 | G40: =VALUE(SUBSTITUTE(Titanic_DATASET[[#This Row],[Age Correción.]],".",",")) -> 5 | H40: 5 | J40: 0 | K40: 0 | L40: 2664 | M40: =VALUE(SUBSTITUTE(N40,".",",")) -> 7225 | N40: 7225 | O40: =IF(ISBLANK(P40),"Desconocido",P40) -> Desconocido | Q40: C
A41: 112 | B41: 0 | C41: 3 | D41: Zabour, Miss. Hileni | E41: female | F41: =ROUNDUP(Titanic_DATASET[[#This Row],[Age Correción 2]],0) -> 15 | G41: =VALUE(SUBSTITUTE(Titanic_DATASET[[#This Row],[Age Correción.]],".",",")) -> 14.5 | H41: 14.5 | I41: 14.5 | J41: 1 | K41: 0 | L41: 2665 | M41: =VALUE(SUBSTITUTE(N41,".",",")) -> 144542 | N41: 144542 | O41: =IF(ISBLANK(P41),"Desconocido",P41) -> Desconocido | Q41: C
A42: 241 | B42: 0 | C42: 3 | D42: Zabour, Miss. Thamine | E42: female | F42: =ROUNDUP(Titanic_DATASET[[#This Row],[Age Correción 2]],0) -> 29 | G42: =VALUE(SUBSTITUTE(Titanic_DATASET[[#This Row],[Age Correción.]],".",",")) -> 29 | H42: 29 | J42: 1 | K42: 0 | L42: 2665 | M42: =VALUE(SUBSTITUTE(N42,".",",")) -> 144542 | N42: 144542 | O42: =IF(ISBLANK(P42),"Desconocido",P42) -> Desconocido | Q42: C
A43: 449 | B43: 1 | C43: 3 | D43: Baclini, Miss. Marie Catherine | E43: female | F43: =ROUNDUP(Titanic_DATASET[[#This Row],[Age Correción 2]],0) -> 5 | G43: =VALUE(SUBSTITUTE(Titanic_DATASET[[#This Row],[Age Correción.]],".",",")) -> 5 | H43: 5 | I43: 5 | J43: 2 | K43: 1 | L43: 2666 | M43: =VALUE(SUBSTITUTE(N43,".",",")) -> 192583 | N43: 192583 | O43: =IF(ISBLANK(P43),"Desconocido",P43) -> Desconocido | Q43: C
A44: 470 | B44: 1 | C44: 3 | D44: Baclini, Miss. Helene Barbara | E44: female | F44: =ROUNDUP(Titanic_DATASET[[#This Row],[Age Correción 2]],0) -> 1 | G44: =VALUE(SUBSTITUTE(Titanic_DATASET[[#This Row],[Age Correción.]],".",",")) -> 0.75 | H44: 0.75 | I44: 0.75 | J44: 2 | K44: 1 | L44: 2666 | M44: =VALUE(SUBSTITUTE(N44,".",",")) -> 192583 | N44: 192583 | O44: =IF(ISBLANK(P44),"Desconocido",P44) -> Desconocido | Q44: C
A45: 645 | B45: 1 | C45: 3 | D45: Baclini, Miss. Eugenie | E45: female | F45: =ROUNDUP(Titanic_DATASET[[#This Row],[Age Correción 2]],0) -> 1 | G45: =VALUE(SUBSTITUTE(Titanic_DATASET[[#This Row],[Age Correción.]],".",",")) -> 0.75 | H45: 0.75 | I45: 0.75 | J45: 2 | K45: 1 | L45: 2666 | M45: =VALUE(SUBSTITUTE(N45,".",",")) -> 192583 | N45: 192583 | O45: =IF(ISBLANK(P45),"Desconocido",P45) -> Desconocido | Q45: C
A46: 859 | B46: 1 | C46: 3 | D46: Baclini, Mrs. Solomon (Latifa Qurban) | E46: female | F46: =ROUNDUP(Titanic_DATASET[[#This Row],[Age Correción 2]],0) -> 24 | G46: =VALUE(SUBSTITUTE(Titanic_DATASET[[#This Row],[Age Correción.]],".",",")) -> 24 | H46: 24 | I46: 24 | J46: 0 | K46: 3 | L46: 2666 | M46: =VALUE(SUBSTITUTE(N46,".",",")) -> 192583 | N46: 192583 | O46: =IF(ISBLANK(P46),"Desconocido",P46) -> Desconocido | Q46: C
A47: 876 | B47: 1 | C47: 3 | D47: Najib, Miss. Adele Kiamie "Jane" | E47: female | F47: =ROUNDUP(Titanic_DATASET[[#This Row],[Age Correción 2]],0) -> 15 | G47: =VALUE(SUBSTITUTE(Titanic_DATASET[[#This Row],[Age Correción.]],".",",")) -> 15 | H47: 15 | I47: 15 | J47: 0 | K47: 0 | L47: 2667 | M47: =VALUE(SUBSTITUTE(N47,".",",")) -> 7225 | N47: 7225 | O47: =IF(ISBLANK(P47),"Desconocido",P47) -> Desconocido | Q47: C
A48: 129 | B48: 1 | C48: 3 | D48: Peter, Miss. Anna | E48: female | F48: =ROUNDUP(Titanic_DATASET[[#This Row],[Age Correción 2]],0) -> 8 | G48: =VALUE(SUBSTITUTE(Titanic_DATASET[[#This Row],[Age Correción.]],".",",")) -> 8 | H48: 8 | J48: 1 | K48: 1 | L48: 2668 | M48: =VALUE(SUBSTITUTE(N48,".",",")) -> 223583 | N48: 223583 | O48: =IF(ISBLANK(P48),"Desconocido",P48) -> F E69 | P48: F E69 | Q48: C
A49: 534 | B49: 1 | C49: 3 | D49: Peter, Mrs. Catherine (Catherine Rizk) | E49: female | F49: =ROUNDUP(Titanic_DATASET[[#This Row],[Age Correción 2]],0) -> 7 | G49: =VALUE(SUBSTITUTE(Titanic_DATASET[[#This Row],[Age Correción.]],".",",")) -> 7 | H49: 7 | J49: 0 | K49: 2 | L49: 2668 | M49: =VALUE(SUBSTITUTE(N49,".",",")) -> 223583 | N49: 223583 | O49: =IF(ISBLANK(P49),"Desconocido",P49) -> Desconocido | Q49: C
A50: 61 | B50: 0 | C50: 3 | D50: Sirayanian, Mr. Orsen | E50: male | F50: =ROUNDUP(Titanic_DATASET[[#This Row],[Age Correción 2]],0) -> 22 | G50: =VALUE(SUBSTITUTE(Titanic_DATASET[[#This Row],[Age Correción.]],".",",")) -> 22 | H50: 22 | I50: 22 | J50: 0 | K50: 0 | L50: 2669 | M50: =VALUE(SUBSTITUTE(N50,".",",")) -> 72292 | N50: 72292 | O50: =IF(ISBLANK(P50),"Desconocido",P50) -> Desconocido | Q50: C
A51: 833 | B51: 0 | C51: 3 | D51: Saad, Mr. Amin | E51: male | F51: =ROUNDUP(Titanic_DATASET[[#This Row],[Age Correción 2]],0) -> 38 | G51: =VALUE(SUBSTITUTE(Titanic_DATASET[[#This Row],[Age Correción.]],".",",")) -> 38 | H51: 38 | J51: 0 | K51: 0 | L51: 2671 | M51: =VALUE(SUBSTITUTE(N51,".",",")) -> 72292 | N51: 72292 | O51: =IF(ISBLANK(P51),"Desconocido",P51) -> Desconocido | Q51: C
A52: 694 | B52: 0 | C52: 3 | D52: Saad, Mr. Khalil | E52: male | F52: =ROUNDUP(Titanic_DATASET[[#This Row],[Age Correción 2]],0) -> 25 | G52: =VALUE(SUBSTITUTE(Titanic_DATASET[[#This Row],[Age Correción.]],".",",")) -> 25 | H52: 25 | I52: 25 | J52: 0 | K52: 0 | L52: 2672 | M52: =VALUE(SUBSTITUTE(N52,".",",")) -> 7225 | N52: 7225 | O52: =IF(ISBLANK(P52),"Desconocido",P52) -> Desconocido | Q52: C
A53: 774 | B53: 0 | C53: 3 | D53: Elias, Mr. Dibo | E53: male | F53: =ROUNDUP(Titanic_DATASET[[#This Row],[Age Correción 2]],0) -> 51 | G53: =VALUE(SUBSTITUTE(Titanic_DATASET[[#This Row],[Age Correción.]],".",",")) -> 51 | H53: 51 | J53: 0 | K53: 0 | L53: 2674 | M53: =VALUE(SUBSTITUTE(N53,".",",")) -> 7225 | N53: 7225 | O53: =IF(ISBLANK(P53),"Desconocido",P53) -> Desconocido | Q53: C
A54: 37 | B54: 1 | C54: 3 | D54: Mamee, Mr. Hanna | E54: male | F54: =ROUNDUP(Titanic_DATASET[[#This Row],[Age Correción 2]],0) -> 69 | G54: =VALUE(SUBSTITUTE(Titanic_DATASET[[#This Row],[Age Correción.]],".",",")) -> 69 | H54: 69 | J54: 0 | K54: 0 | L54: 2677 | M54: =VALUE(SUBSTITUTE(N54,".",",")) -> 72292 | N54: 72292 | O54: =IF(ISBLANK(P54),"Desconocido",P54) -> Desconocido | Q54: C
A55: 141 | B55: 0 | C55: 3 | D55: Boulos, Mrs. Joseph (Sultana) | E55: female | F55: =ROUNDUP(Titanic_DATASET[[#This Row],[Age Correción 2]],0) -> 74 | G55: =VALUE(SUBSTITUTE(Titanic_DATASET[[#This Row],[Age Correción.]],".",",")) -> 74 | H55: 74 | J55: 0 | K55: 2 | L55: 2678 | M55: =VALUE(SUBSTITUTE(N55,".",",")) -> 152458 | N55: 152458 | O55: =IF(ISBLANK(P55),"Desconocido",P55) -> Desconocido | Q55: C
A56: 853 | B56: 0 | C56: 3 | D56: Boulos, Miss. Nourelain | E56: female | F56: =ROUNDUP(Titanic_DATASET[[#This Row],[Age Correción 2]],0) -> 9 | G56: =VALUE(SUBSTITUTE(Titanic_DATASET[[#This Row],[Age Correción.]],".",",")) -> 9 | H56: 9 | I56: 9 | J56: 1 | K56: 1 | L56: 2678 | M56: =VALUE(SUBSTITUTE(N56,".",",")) -> 152458 | N56: 152458 | O56: =IF(ISBLANK(P56),"Desconocido",P56) -> Desconocido | Q56: C
A57: 74 | B57: 0 | C57: 3 | D57: Chronopoulos, Mr. Apostolos | E57: male | F57: =ROUNDUP(Titanic_DATASET[[#This Row],[Age Correción 2]],0) -> 26 | G57: =VALUE(SUBSTITUTE(Titanic_DATASET[[#This Row],[Age Correción.]],".",",")) -> 26 | H57: 26 | I57: 26 | J57: 1 | K57: 0 | L57: 2680 | M57: =VALUE(SUBSTITUTE(N57,".",",")) -> 144542 | N57: 144542 | O57: =IF(ISBLANK(P57),"Desconocido",P57) -> Desconocido | Q57: C
A58: 844 | B58: 0 | C58: 3 | D58: Lemberopolous, Mr. Peter L | E58: male | F58: =ROUNDUP(Titanic_DATASET[[#This Row],[Age Correción 2]],0) -> 35 | G58: =VALUE(SUBSTITUTE(Titanic_DATASET[[#This Row],[Age Correción.]],".",",")) -> 34.5 | H58: 34.5 | I58: 34.5 | J58: 0 | K58: 0 | L58: 2683 | M58: =VALUE(SUBSTITUTE(N58,".",",")) -> 64375 | N58: 64375 | O58: =IF(ISBLANK(P58),"Desconocido",P58) -> Desconocido | Q58: C
A59: 799 | B59: 0 | C59: 3 | D59: Ibrahim Shawah, Mr. Yousseff | E59: male | F59: =ROUNDUP(Titanic_DATASET[[#This Row],[Age Correción 2]],0) -> 30 | G59: =VALUE(SUBSTITUTE(Titanic_DATASET[[#This Row],[Age Correción.]],".",",")) -> 30 | H59: 30 | I59: 30 | J59: 0 | K59: 0 | L59: 2685 | M59: =VALUE(SUBSTITUTE(N59,".",",")) -> 72292 | N59: 72292 | O59: =IF(ISBLANK(P59),"Desconocido",P59) -> Desconocido | Q59: C
A60: 569 | B60: 0 | C60: 3 | D60: Doharr, Mr. Tannous | E60: male | F60: =ROUNDUP(Titanic_DATASET[[#This Row],[Age Correción 2]],0) -> 11 | G60: =VALUE(SUBSTITUTE(Titanic_DATASET[[#This Row],[Age Correción.]],".",",")) -> 11 | H60: 11 | J60: 0 | K60: 0 | L60: 2686 | M60: =VALUE(SUBSTITUTE(N60,".",",")) -> 72292 | N60: 72292 | O60: =IF(ISBLANK(P60),"Desconocido",P60) -> Desconocido | Q60: C
A61: 781 | B61: 1 | C61: 3 | D61: Ayoub, Miss. Banoura | E61: female | F61: =ROUNDUP(Titanic_DATASET[[#This Row],[Age Correción 2]],0) -> 13 | G61: =VALUE(SUBSTITUTE(Titanic_DATASET[[#This Row],[Age Correción.]],".",",")) -> 13 | H61: 13 | I61: 13 | J61: 0 | K61: 0 | L61: 2687 | M61: =VALUE(SUBSTITUTE(N61,".",",")) -> 72292 | N61: 72292 | O61: =IF(ISBLANK(P61),"Desconocido",P61) -> Desconocido | Q61: C
A62: 579 | B62: 0 | C62: 3 | D62: Caram, Mrs. Joseph (Maria Elias) | E62: female | F62: =ROUNDUP(Titanic_DATASET[[#This Row],[Age Correción 2]],0) -> 13 | G62: =VALUE(SUBSTITUTE(Titanic_DATASET[[#This Row],[Age Correción.]],".",",")) -> 13 | H62: 13 | J62: 1 | K62: 0 | L62: 2689 | M62: =VALUE(SUBSTITUTE(N62,".",",")) -> 144583 | N62: 144583 | O62: =IF(ISBLANK(P62),"Desconocido",P62) -> Desconocido | Q62: C
A63: 533 | B63: 0 | C63: 3 | D63: Elias, Mr. Joseph Jr | E63: male | F63: =ROUNDUP(Titanic_DATASET[[#This Row],[Age Correción 2]],0) -> 17 | G63: =VALUE(SUBSTITUTE(Titanic_DATASET[[#This Row],[Age Correción.]],".",",")) -> 17 | H63: 17 | I63: 17 | J63: 1 | K63: 1 | L63: 2690 | M63: =VALUE(SUBSTITUTE(N63,".",",")) -> 72292 | N63: 72292 | O63: =IF(ISBLANK(P63),"Desconocido",P63) -> Desconocido | Q63: C
A64: 363 | B64: 0 | C64: 3 | D64: Barbara, Mrs. (Catherine David) | E64: female | F64: =ROUNDUP(Titanic_DATASET[[#This Row],[Age Correción 2]],0) -> 45 | G64: =VALUE(SUBSTITUTE(Titanic_DATASET[[#This Row],[Age Correción.]],".",",")) -> 45 | H64: 45 | I64: 45 | J64: 0 | K64: 1 | L64: 2691 | M64: =VALUE(SUBSTITUTE(N64,".",",")) -> 144542 | N64: 144542 | O64: =IF(ISBLANK(P64),"Desconocido",P64) -> Desconocido | Q64: C
A65: 703 | B65: 0 | C65: 3 | D65: Barbara, Miss. Saiide | E65: female | F65: =ROUNDUP(Titanic_DATASET[[#This Row],[Age Correción 2]],0) -> 18 | G65: =VALUE(SUBSTITUTE(Titanic_DATASET[[#This Row],[Age Correción.]],".",",")) -> 18 | H65: 18 | I65: 18 | J65: 0 | K65: 1 | L65: 2691 | M65: =VALUE(SUBSTITUTE(N65,".",",")) -> 144542 | N65: 144542 | O65: =IF(ISBLANK(P65),"Desconocido",P65) -> Desconocido | Q65: C
A66: 297 | B66: 0 | C66: 3 | D66: Hanna, Mr. Mansour | E66: male | F66: =ROUNDUP(Titanic_DATASET[[#This Row],[Age Correción 2]],0) -> 24 | G66: =VALUE(SUBSTITUTE(Titanic_DATASET[[#This Row],[Age Correción.]],".",",")) -> 23.5 | H66: 23.5 | I66: 23.5 | J66: 0 | K66: 0 | L66: 2693 | M66: =VALUE(SUBSTITUTE(N66,".",",")) -> 72292 | N66: 72292 | O66: =IF(ISBLANK(P66),"Desconocido",P66) -> Desconocido | Q66: C
A67: 245 | B67: 0 | C67: 3 | D67: Attalah, Mr. Sleiman | E67: male | F67: =ROUNDUP(Titanic_DATASET[[#This Row],[Age Correción 2]],0) -> 30 | G67: =VALUE(SUBSTITUTE(Titanic_DATASET[[#This Row],[Age Correción.]],".",",")) -> 30 | H67: 30 | I67: 30 | J67: 0 | K67: 0 | L67: 2694 | M67: =VALUE(SUBSTITUTE(N67,".",",")) -> 7225 | N67: 7225 | O67: =IF(ISBLANK(P67),"Desconocido",P67) -> Desconocido | Q67: C
A68: 353 | B68: 0 | C68: 3 | D68: Elias, Mr. Tannous | E68: male | F68: =ROUNDUP(Titanic_DATASET[[#This Row],[Age Correción 2]],0) -> 15 | G68: =VALUE(SUBSTITUTE(Titanic_DATASET[[#This Row],[Age Correción.]],".",",")) -> 15 | H68: 15 | I68: 15 | J68: 1 | K68: 1 | L68: 2695 | M68: =VALUE(SUBSTITUTE(N68,".",",")) -> 72292 | N68: 72292 | O68: =IF(ISBLANK(P68),"Desconocido",P68) -> Desconocido | Q68: C
A69: 58 | B69: 0 | C69: 3 | D69: Novel, Mr. Mansouer | E69: male | F69: =ROUNDUP(Titanic_DATASET[[#This Row],[Age Correción 2]],0) -> 29 | G69: =VALUE(SUBSTITUTE(Titanic_DATASET[[#This Row],[Age Correción.]],".",",")) -> 28.5 | H69: 28.5 | I69: 28.5 | J69: 0 | K69: 0 | L69: 2697 | M69: =VALUE(SUBSTITUTE(N69,".",",")) -> 72292 | N69: 72292 | O69: =IF(ISBLANK(P69),"Desconocido",P69) -> Desconocido | Q69: C
A70: 208 | B70: 1 | C70: 3 | D70: Albimona, Mr. Nassef Cassem | E70: male | F70: =ROUNDUP(Titanic_DATASET[[#This Row],[Age Correción 2]],0) -> 26 | G70: =VALUE(SUBSTITUTE(Titanic_DATASET[[#This Row],[Age Correción.]],".",",")) -> 26 | H70: 26 | I70: 26 | J70: 0 | K70: 0 | L70: 2699 | M70: =VALUE(SUBSTITUTE(N70,".",",")) -> 187875 | N70: 187875 | O70: =IF(ISBLANK(P70),"Desconocido",P70) -> Desconocido | Q70: C
A71: 732 | B71: 0 | C71: 3 | D71: Hassan, Mr. Houssein G N | E71: male | F71: =ROUNDUP(Titanic_DATASET[[#This Row],[Age Correción 2]],0) -> 11 | G71: =VALUE(SUBSTITUTE(Titanic_DATASET[[#This Row],[Age Correción.]],".",",")) -> 11 | H71: 11 | I71: 11 | J71: 0 | K71: 0 | L71: 2699 | M71: =VALUE(SUBSTITUTE(N71,".",",")) -> 187875 | N71: 187875 | O71: =IF(ISBLANK(P71),"Desconocido",P71) -> Desconocido | Q71: C
A72: 525 | B72: 0 | C72: 3 | D72: Kassem, Mr. Fared | E72: male | F72: =ROUNDUP(Titanic_DATASET[[#This Row],[Age Correción 2]],0) -> 41 | G72: =VALUE(SUBSTITUTE(Titanic_DATASET[[#This Row],[Age Correción.]],".",",")) -> 41 | H72: 41 | J72: 0 | K72: 0 | L72: 2700 | M72: =VALUE(SUBSTITUTE(N72,".",",")) -> 72292 | N72: 72292 | O72: =IF(ISBLANK(P72),"Desconocido",P72) -> Desconocido | Q72: C
A73: 544 | B73: 1 | C73: 2 | D73: Beane, Mr. Edward | E73: male | F73: =ROUNDUP(Titanic_DATASET[[#This Row],[Age Correción 2]],0) -> 32 | G73: =VALUE(SUBSTITUTE(Titanic_DATASET[[#This Row],[Age Correción.]],".",",")) -> 32 | H73: 32 | I73: 32 | J73: 1 | K73: 0 | L73: 2908 | M73: =VALUE(SUBSTITUTE(N73,".",",")) -> 26 | N73: 26 | O73: =IF(ISBLANK(P73),"Desconocido",P73) -> Desconocido | Q73: S
A74: 547 | B74: 1 | C74: 2 | D74: Beane, Mrs. Edward (Ethel Clarke) | E74: female | F74: =ROUNDUP(Titanic_DATASET[[#This Row],[Age Correción 2]],0) -> 19 | G74: =VALUE(SUBSTITUTE(Titanic_DATASET[[#This Row],[Age Correción.]],".",",")) -> 19 | H74: 19 | I74: 19 | J74: 1 | K74: 0 | L74: 2908 | M74: =VALUE(SUBSTITUTE(N74,".",",")) -> 26 | N74: 26 | O74: =IF(ISBLANK(P74),"Desconocido",P74) -> Desconocido | Q74: S
A75: 54 | B75: 1 | C75: 2 | D75: Faunthorpe, Mrs. Lizzie (Elizabeth Anne Wilkinson) | E75: female | F75: =ROUNDUP(Titanic_DATASET[[#This Row],[Age Correción 2]],0) -> 29 | G75: =VALUE(SUBSTITUTE(Titanic_DATASET[[#This Row],[Age Correción.]],".",",")) -> 29 | H75: 29 | I75: 29 | J75: 1 | K75: 0 | L75: 2926 | M75: =VALUE(SUBSTITUTE(N75,".",",")) -> 26 | N75: 26 | O75: =IF(ISBLANK(P75),"Desconocido",P75) -> Desconocido | Q75: S
A76: 585 | B76: 0 | C76: 3 | D76: Paulner, Mr. Uscher | E76: male | F76: =ROUNDUP(Titanic_DATASET[[#This Row],[Age Correción 2]],0) -> 41 | G76: =VALUE(SUBSTITUTE(Titanic_DATASET[[#This Row],[Age Correción.]],".",",")) -> 41 | H76: 41 | J76: 0 | K76: 0 | L76: 3411 | M76: =VALUE(SUBSTITUTE(N76,".",",")) -> 87125 | N76: 87125 | O76: =IF(ISBLANK(P76),"Desconocido",P76) -> Desconocido | Q76: C
A77: 478 | B77: 0 | C77: 3 | D77: Braund, Mr. Lewis Richard | E77: male | F77: =ROUNDUP(Titanic_DATASET[[#This Row],[Age Correción 2]],0) -> 29 | G77: =VALUE(SUBSTITUTE(Titanic_DATASET[[#This Row],[Age Correción.]],".",",")) -> 29 | H77: 29 | I77: 29 | J77: 1 | K77: 0 | L77: 3460 | M77: =VALUE(SUBSTITUTE(N77,".",",")) -> 70458 | N77: 70458 | O77: =IF(ISBLANK(P77),"Desconocido",P77) -> Desconocido | Q77: S
A78: 811 | B78: 0 | C78: 3 | D78: Alexander, Mr. William | E78: male | F78: =ROUNDUP(Titanic_DATASET[[#This Row],[Age Correción 2]],0) -> 26 | G78: =VALUE(SUBSTITUTE(Titanic_DATASET[[#This Row],[Age Correción.]],".",",")) -> 26 | H78: 26 | I78: 26 | J78: 0 | K78: 0 | L78: 3474 | M78: =VALUE(SUBSTITUTE(N78,".",",")) -> 78875 | N78: 78875 | O78: =IF(ISBLANK(P78),"Desconocido",P78) -> Desconocido | Q78: S
A79: 177 | B79: 0 | C79: 3 | D79: Lefebre, Master. Henry Forbes | E79: male | F79: =ROUNDUP(Titanic_DATASET[[#This Row],[Age Correción 2]],0) -> 36 | G79: =VALUE(SUBSTITUTE(Titanic_DATASET[[#This Row],[Age Correción.]],".",",")) -> 36 | H79: 36 | J79: 3 | K79: 1 | L79: 4133 | M79: =VALUE(SUBSTITUTE(N79,".",",")) -> 254667 | N79: 254667 | O79: =IF(ISBLANK(P79),"Desconocido",P79) -> Desconocido | Q79: S
A80: 230 | B80: 0 | C80: 3 | D80: Lefebre, Miss. Mathilde | E80: female | F80: =ROUNDUP(Titanic_DATASET[[#This Row],[Age Correción 2]],0) -> 45 | G80: =VALUE(SUBSTITUTE(Titanic_DATASET[[#This Row],[Age Correción.]],".",",")) -> 45 | H80: 45 | J80: 3 | K80: 1 | L80: 4133 | M80: =VALUE(SUBSTITUTE(N80,".",",")) -> 254667 | N80: 254667 | O80: =IF(ISBLANK(P80),"Desconocido",P80) -> Desconocido | Q80: S
A81: 410 | B81: 0 | C81: 3 | D81: Lefebre, Miss. Ida | E81: female | F81: =ROUNDUP(Titanic_DATASET[[#This Row],[Age Correción 2]],0) -> 65 | G81: =VALUE(SUBSTITUTE(Titanic_DATASET[[#This Row],[Age Correción.]],".",",")) -> 65 | H81: 65 | J81: 3 | K81: 1 | L81: 4133 | M81: =VALUE(SUBSTITUTE(N81,".",",")) -> 254667 | N81: 254667 | O81: =IF(ISBLANK(P81),"Desconocido",P81) -> Desconocido | Q81: S
A82: 486 | B82: 0 | C82: 3 | D82: Lefebre, Miss. Jeannie | E82: female | F82: =ROUNDUP(Titanic_DATASET[[#This Row],[Age Correción 2]],0) -> 60 | G82: =VALUE(SUBSTITUTE(Titanic_DATASET[[#This Row],[Age Correción.]],".",",")) -> 60 | H82: 60 | J82: 3 | K82: 1 | L82: 4133 | M82: =VALUE(SUBSTITUTE(N82,".",",")) -> 254667 | N82: 254667 | O82: =IF(ISBLANK(P82),"Desconocido",P82) -> Desconocido | Q82: S
A83: 484 | B83: 1 | C83: 3 | D83: Turkula, Mrs. (Hedwig) | E83: female | F83: =ROUNDUP(Titanic_DATASET[[#This Row],[Age Correción 2]],0) -> 63 | G83: =VALUE(SUBSTITUTE(Titanic_DATASET[[#This Row],[Age Correción.]],".",",")) -> 63 | H83: 63 | I83: 63 | J83: 0 | K83: 0 | L83: 4134 | M83: =VALUE(SUBSTITUTE(N83,".",",")) -> 95875 | N83: 95875 | O83: =IF(ISBLANK(P83),"Desconocido",P83) -> Desconocido | Q83: S
A84: 504 | B84: 0 | C84: 3 | D84: Laitinen, Miss. Kristina Sofia | E84: female | F84: =ROUNDUP(Titanic_DATASET[[#This Row],[Age Correción 2]],0) -> 37 | G84: =VALUE(SUBSTITUTE(Titanic_DATASET[[#This Row],[Age Correción.]],".",",")) -> 37 | H84: 37 | I84: 37 | J84: 0 | K84: 0 | L84: 4135 | M84: =VALUE(SUBSTITUTE(N84,".",",")) -> 95875 | N84: 95875 | O84: =IF(ISBLANK(P84),"Desconocido",P84) -> Desconocido | Q84: S
A85: 114 | B85: 0 | C85: 3 | D85: Jussila, Miss. Katriina | E85: female | F85: =ROUNDUP(Titanic_DATASET[[#This Row],[Age Correción 2]],0) -> 20 | G85: =VALUE(SUBSTITUTE(Titanic_DATASET[[#This Row],[Age Correción.]],".",",")) -> 20 | H85: 20 | I85: 20 | J85: 1 | K85: 0 | L85: 4136 | M85: =VALUE(SUBSTITUTE(N85,".",",")) -> 9825 | N85: 9825 | O85: =IF(ISBLANK(P85),"Desconocido",P85) -> Desconocido | Q85: S
A86: 403 | B86: 0 | C86: 3 | D86: Jussila, Miss. Mari Aina | E86: female | F86: =ROUNDUP(Titanic_DATASET[[#This Row],[Age Correción 2]],0) -> 21 | G86: =VALUE(SUBSTITUTE(Titanic_DATASET[[#This Row],[Age Correción.]],".",",")) -> 21 | H86: 21 | I86: 21 | J86: 1 | K86: 0 | L86: 4137 | M86: =VALUE(SUBSTITUTE(N86,".",",")) -> 9825 | N86: 9825 | O86: =IF(ISBLANK(P86),"Desconocido",P86) -> Desconocido | Q86: S
A87: 678 | B87: 1 | C87: 3 | D87: Turja, Miss. Anna Sofia | E87: female | F87: =ROUNDUP(Titanic_DATASET[[#This Row],[Age Correción 2]],0) -> 18 | G87: =VALUE(SUBSTITUTE(Titanic_DATASET[[#This Row],[Age Correción.]],".",",")) -> 18 | H87: 18 | I87: 18 | J87: 0 | K87: 0 | L87: 4138 | M87: =VALUE(SUBSTITUTE(N87,".",",")) -> 98417 | N87: 98417 | O87: =IF(ISBLANK(P87),"Desconocido",P87) -> Desconocido | Q87: S
A88: 198 | B88: 0 | C88: 3 | D88: Olsen, Mr. Karl Siegwart Andreas | E88: male | F88: =ROUNDUP(Titanic_DATASET[[#This Row],[Age Correción 2]],0) -> 42 | G88: =VALUE(SUBSTITUTE(Titanic_DATASET[[#This Row],[Age Correción.]],".",",")) -> 42 | H88: 42 | I88: 42 | J88: 0 | K88: 1 | L88: 4579 | M88: =VALUE(SUBSTITUTE(N88,".",",")) -> 84042 | N88: 84042 | O88: =IF(ISBLANK(P88),"Desconocido",P88) -> Desconocido | Q88: S
A89: 663 | B89: 0 | C89: 1 | D89: Colley, Mr. Edward Pomeroy | E89: male | F89: =ROUNDUP(Titanic_DATASET[[#This Row],[Age Correción 2]],0) -> 47 | G89: =VALUE(SUBSTITUTE(Titanic_DATASET[[#This Row],[Age Correción.]],".",",")) -> 47 | H89: 47 | I89: 47 | J89: 0 | K89: 0 | L89: 5727 | M89: =VALUE(SUBSTITUTE(N89,".",",")) -> 255875 | N89: 255875 | O89: =IF(ISBLANK(P89),"Desconocido",P89) -> E58 | P89: E58 | Q89: S
A90: 683 | B90: 0 | C90: 3 | D90: Olsvigen, Mr. Thor Anderson | E90: male | F90: =ROUNDUP(Titanic_DATASET[[#This Row],[Age Correción 2]],0) -> 20 | G90: =VALUE(SUBSTITUTE(Titanic_DATASET[[#This Row],[Age Correción.]],".",",")) -> 20 | H90: 20 | I90: 20 | J90: 0 | K90: 0 | L90: 6563 | M90: =VALUE(SUBSTITUTE(N90,".",",")) -> 9225 | N90: 9225 | O90: =IF(ISBLANK(P90),"Desconocido",P90) -> Desconocido | Q90: S
A91: 351 | B91: 0 | C91: 3 | D91: Odahl, Mr. Nils Martin | E91: male | F91: =ROUNDUP(Titanic_DATASET[[#This Row],[Age Correción 2]],0) -> 23 | G91: =VALUE(SUBSTITUTE(Titanic_DATASET[[#This Row],[Age Correción.]],".",",")) -> 23 | H91: 23 | I91: 23 | J91: 0 | K91: 0 | L91: 7267 | M91: =VALUE(SUBSTITUTE(N91,".",",")) -> 9225 | N91: 9225 | O91: =IF(ISBLANK(P91),"Desconocido",P91) -> Desconocido | Q91: S
A92: 139 | B92: 0 | C92: 3 | D92: Osen, Mr. Olaf Elon | E92: male | F92: =ROUNDUP(Titanic_DATASET[[#This Row],[Age Correción 2]],0) -> 16 | G92: =VALUE(SUBSTITUTE(Titanic_DATASET[[#This Row],[Age Correción.]],".",",")) -> 16 | H92: 16 | I92: 16 | J92: 0 | K92: 0 | L92: 7534 | M92: =VALUE(SUBSTITUTE(N92,".",",")) -> 92167 | N92: 92167 | O92: =IF(ISBLANK(P92),"Desconocido",P92) -> Desconocido | Q92: S
A93: 877 | B93: 0 | C93: 3 | D93: Gustafsson, Mr. Alfred Ossian | E93: male | F93: =ROUNDUP(Titanic_DATASET[[#This Row],[Age Correción 2]],0) -> 20 | G93: =VALUE(SUBSTITUTE(Titanic_DATASET[[#This Row],[Age Correción.]],".",",")) -> 20 | H93: 20 | I93: 20 | J93: 0 | K93: 0 | L93: 7534 | M93: =VALUE(SUBSTITUTE(N93,".",",")) -> 98458 | N93: 98458 | O93: =IF(ISBLANK(P93),"Desconocido",P93) -> Desconocido | Q93: S
A94: 104 | B94: 0 | C94: 3 | D94: Johansson, Mr. Gustaf Joel | E94: male | F94: =ROUNDUP(Titanic_DATASET[[#This Row],[Age Correción 2]],0) -> 33 | G94: =VALUE(SUBSTITUTE(Titanic_DATASET[[#This Row],[Age Correción.]],".",",")) -> 33 | H94: 33 | I94: 33 | J94: 0 | K94: 0 | L94: 7540 | M94: =VALUE(SUBSTITUTE(N94,".",",")) -> 86542 | N94: 86542 | O94: =IF(ISBLANK(P94),"Desconocido",P94) -> Desconocido | Q94: S
A95: 714 | B95: 0 | C95: 3 | D95: Larsson, Mr. August Viktor | E95: male | F95: =ROUNDUP(Titanic_DATASET[[#This Row],[Age Correción 2]],0) -> 29 | G95: =VALUE(SUBSTITUTE(Titanic_DATASET[[#This Row],[Age Correción.]],".",",")) -> 29 | H95: 29 | I95: 29 | J95: 0 | K95: 0 | L95: 7545 | M95: =VALUE(SUBSTITUTE(N95,".",",")) -> 94833 | N95: 94833 | O95: =IF(ISBLANK(P95),"Desconocido",P95) -> Desconocido | Q95: S
A96: 41 | B96: 0 | C96: 3 | D96: Ahlin, Mrs. Johan (Johanna Persdotter Larsson) | E96: female | F96: =ROUNDUP(Titanic_DATASET[[#This Row],[Age Correción 2]],0) -> 40 | G96: =VALUE(SUBSTITUTE(Titanic_DATASET[[#This Row],[Age Correción.]],".",",")) -> 40 | H96: 40 | I96: 40 | J96: 1 | K96: 0 | L96: 7546 | M96: =VALUE(SUBSTITUTE(N96,".",",")) -> 9475 | N96: 9475 | O96: =IF(ISBLANK(P96),"Desconocido",P96) -> Desconocido | Q96: S
A97: 883 | B97: 0 | C97: 3 | D97: Dahlberg, Miss. Gerda Ulrika | E97: female | F97: =ROUNDUP(Titanic_DATASET[[#This Row],[Age Correción 2]],0) -> 22 | G97: =VALUE(SUBSTITUTE(Titanic_DATASET[[#This Row],[Age Correción.]],".",",")) -> 22 | H97: 22 | I97: 22 | J97: 0 | K97: 0 | L97: 7552 | M97: =VALUE(SUBSTITUTE(N97,".",",")) -> 105167 | N97: 105167 | O97: =IF(ISBLANK(P97),"Desconocido",P97) -> Desconocido | Q97: S
A98: 475 | B98: 0 | C98: 3 | D98: Strandberg, Miss. Ida Sofia | E98: female | F98: =ROUNDUP(Titanic_DATASET[[#This Row],[Age Correción 2]],0) -> 22 | G98: =VALUE(SUBSTITUTE(Titanic_DATASET[[#This Row],[Age Correción.]],".",",")) -> 22 | H98: 22 | I98: 22 | J98: 0 | K98: 0 | L98: 7553 | M98: =VALUE(SUBSTITUTE(N98,".",",")) -> 98375 | N98: 98375 | O98: =IF(ISBLANK(P98),"Desconocido",P98) -> Desconocido | Q98: S
A99: 339 | B99: 1 | C99: 3 | D99: Dahl, Mr. Karl Edwart | E99: male | F99: =ROUNDUP(Titanic_DATASET[[#This Row],[Age Correción 2]],0) -> 45 | G99: =VALUE(SUBSTITUTE(Titanic_DATASET[[#This Row],[Age Correción.]],".",",")) -> 45 | H99: 45 | I99: 45 | J99: 0 | K99: 0 | L99: 7598 | M99: =VALUE(SUBSTITUTE(N99,".",",")) -> 8.05 | N99: 8.05 | O99: =IF(ISBLANK(P99),"Desconocido",P99) -> Desconocido | Q99: S
A100: 770 | B100: 0 | C100: 3 | D100: Gronnestad, Mr. Daniel Danielsen | E100: male | F100: =ROUNDUP(Titanic_DATASET[[#This Row],[Age Correción 2]],0) -> 32 | G100: =VALUE(SUBSTITUTE(Titanic_DATASET[[#This Row],[Age Correción.]],".",",")) -> 32 | H100: 32 | I100: 32 | J100: 0 | K100: 0 | L100: 8471 | M100: =VALUE(SUBSTITUTE(N100,".",",")) -> 83625 | N100: 83625 | O100: =IF(ISBLANK(P100),"Desconocido",P100) -> Desconocido | Q100: S
A101: 653 | B101: 0 | C101: 3 | D101: Kalvik, Mr. Johannes Halvorsen | E101: male | F101: =ROUNDUP(Titanic_DATASET[[#This Row],[Age Correción 2]],0) -> 21 | G101: =VALUE(SUBSTITUTE(Titanic_DATASET[[#This Row],[Age Correción.]],".",",")) -> 21 | H101: 21 | I101: 21 | J101: 0 | K101: 0 | L101: 8475 | M101: =VALUE(SUBSTITUTE(N101,".",",")) -> 84333 | N101: 84333 | O101: =IF(ISBLANK(P101),"Desconocido",P101) -> Desconocido | Q101: S
A102: 301 | B102: 1 | C102: 3 | D102: Kelly, Miss. Anna Katherine "Annie Kate" | E102: female | F102: =ROUNDUP(Titanic_DATASET[[#This Row],[Age Correción 2]],0) -> 43 | G102: =VALUE(SUBSTITUTE(Titanic_DATASET[[#This Row],[Age Correción.]],".",",")) -> 43 | H102: 43 | J102: 0 | K102: 0 | L102: 9234 | M102: =VALUE(SUBSTITUTE(N102,".",",")) -> 7.75 | N102: 7.75 | O102: =IF(ISBLANK(P102),"Desconocido",P102) -> Desconocido | Q102: Q
...

Sheet DATASET_CLEAN
A3: Nombre | B3: Sexo | C3: ID_Pasajero | D3: Edad | E3: Padres_Hijos | F3: Hermanos/Cónyuge | G3: Clase_Del_Pasaje | H3: Sobreviviente | I3: Ticket | J3: Tarifa | K3: Cabina | L3: Embarque | M3: Rango Etario
A4: Braund, Mr. Owen Harris | B4: male | C4: 1 | D4: 64 | E4: 0 | F4: 1 | G4: 3 | H4: 0 | I4: 693 | J4: 7.25 | K4: Desconocido | L4: S | M4: {=_xlfn.IFS(INFO_Pasajeros[[#This Row],[Edad]]<=13,"Niños",INFO_Pasajeros[[#This Row],[Edad]]<=18,"Jóvenes",INFO_Pasajeros[[#This Row],[Edad]]<=50,"Adultos",INFO_Pasajeros[[#This Row],[Edad]]>=51,"Adultos Mayores")} -> Adultos Mayores
A5: Cumings, Mrs. John Bradley (Florence Briggs Thayer) | B5: female | C5: 2 | D5: 33 | E5: 0 | F5: 1 | G5: 1 | H5: 1 | I5: 695 | J5: 712.833 | K5: B51 B53 B55 | L5: S | M5: {=_xlfn.IFS(INFO_Pasajeros[[#This Row],[Edad]]<=13,"Niños",INFO_Pasajeros[[#This Row],[Edad]]<=18,"Jóvenes",INFO_Pasajeros[[#This Row],[Edad]]<=50,"Adultos",INFO_Pasajeros[[#This Row],[Edad]]>=51,"Adultos Mayores")} -> Adultos
A6: Heikkinen, Miss. Laina | B6: female | C6: 3 | D6: 32 | E6: 0 | F6: 0 | G6: 3 | H6: 1 | I6: 1601 | J6: 7.925 | K6: Desconocido | L6: S | M6: {=_xlfn.IFS(INFO_Pasajeros[[#This Row],[Edad]]<=13,"Niños",INFO_Pasajeros[[#This Row],[Edad]]<=18,"Jóvenes",INFO_Pasajeros[[#This Row],[Edad]]<=50,"Adultos",INFO_Pasajeros[[#This Row],[Edad]]>=51,"Adultos Mayores")} -> Adultos
A7: Futrelle, Mrs. Jacques Heath (Lily May Peel) | B7: female | C7: 4 | D7: 28 | E7: 0 | F7: 1 | G7: 1 | H7: 1 | I7: 1601 | J7: 53.1 | K7: Desconocido | L7: S | M7: {=_xlfn.IFS(INFO_Pasajeros[[#This Row],[Edad]]<=13,"Niños",INFO_Pasajeros[[#This Row],[Edad]]<=18,"Jóvenes",INFO_Pasajeros[[#This Row],[Edad]]<=50,"Adultos",INFO_Pasajeros[[#This Row],[Edad]]>=51,"Adultos Mayores")} -> Adultos
A8: Allen, Mr. William Henry | B8: male | C8: 5 | D8: 26 | E8: 0 | F8: 0 | G8: 3 | H8: 0 | I8: 1601 | J8: 8.05 | K8: Desconocido | L8: S | M8: {=_xlfn.IFS(INFO_Pasajeros[[#This Row],[Edad]]<=13,"Niños",INFO_Pasajeros[[#This Row],[Edad]]<=18,"Jóvenes",INFO_Pasajeros[[#This Row],[Edad]]<=50,"Adultos",INFO_Pasajeros[[#This Row],[Edad]]>=51,"Adultos Mayores")} -> Adultos
A9: Moran, Mr. James | B9: male | C9: 6 | D9: 42 | E9: 0 | F9: 0 | G9: 3 | H9: 0 | I9: 1601 | J9: 84.583 | K9: Desconocido | L9: S | M9: {=_xlfn.IFS(INFO_Pasajeros[[#This Row],[Edad]]<=13,"Niños",INFO_Pasajeros[[#This Row],[Edad]]<=18,"Jóvenes",INFO_Pasajeros[[#This Row],[Edad]]<=50,"Adultos",INFO_Pasajeros[[#This Row],[Edad]]>=51,"Adultos Mayores")} -> Adultos
A10: McCarthy, Mr. Timothy J | B10: male | C10: 7 | D10: 58 | E10: 0 | F10: 0 | G10: 1 | H10: 0 | I10: 1601 | J10: 518.625 | K10: Desconocido | L10: S | M10: {=_xlfn.IFS(INFO_Pasajeros[[#This Row],[Edad]]<=13,"Niños",INFO_Pasajeros[[#This Row],[Edad]]<=18,"Jóvenes",INFO_Pasajeros[[#This Row],[Edad]]<=50,"Adultos",INFO_Pasajeros[[#This Row],[Edad]]>=51,"Adultos Mayores")} -> Adultos Mayores
A11: Palsson, Master. Gosta Leonard | B11: male | C11: 8 | D11: 57 | E11: 1 | F11: 3 | G11: 3 | H11: 0 | I11: 1601 | J11: 21.075 | K11: Desconocido | L11: S | M11: {=_xlfn.IFS(INFO_Pasajeros[[#This Row],[Edad]]<=13,"Niños",INFO_Pasajeros[[#This Row],[Edad]]<=18,"Jóvenes",INFO_Pasajeros[[#This Row],[Edad]]<=50,"Adultos",INFO_Pasajeros[[#This Row],[Edad]]>=51,"Adultos Mayores")} -> Adultos Mayores
A12: Johnson, Mrs. Oscar W (Elisabeth Vilhelmina Berg) | B12: female | C12: 9 | D12: 32 | E12: 2 | F12: 0 | G12: 3 | H12: 1 | I12: 1601 | J12: 111.333 | K12: Desconocido | L12: S | M12: {=_xlfn.IFS(INFO_Pasajeros[[#This Row],[Edad]]<=13,"Niños",INFO_Pasajeros[[#This Row],[Edad]]<=18,"Jóvenes",INFO_Pasajeros[[#This Row],[Edad]]<=50,"Adultos",INFO_Pasajeros[[#This Row],[Edad]]>=51,"Adultos Mayores")} -> Adultos
A13: Nasser, Mrs. Nicholas (Adele Achem) | B13: female | C13: 10 | D13: 28 | E13: 0 | F13: 1 | G13: 2 | H13: 1 | I13: 2003 | J13: 300.708 | K13: Desconocido | L13: S | M13: {=_xlfn.IFS(INFO_Pasajeros[[#This Row],[Edad]]<=13,"Niños",INFO_Pasajeros[[#This Row],[Edad]]<=18,"Jóvenes",INFO_Pasajeros[[#This Row],[Edad]]<=50,"Adultos",INFO_Pasajeros[[#This Row],[Edad]]>=51,"Adultos Mayores")} -> Adultos
A14: Sandstrom, Miss. Marguerite Rut | B14: female | C14: 11 | D14: 18 | E14: 1 | F14: 1 | G14: 3 | H14: 1 | I14: 2223 | J14: 16.7 | K14: Desconocido | L14: S | M14: {=_xlfn.IFS(INFO_Pasajeros[[#This Row],[Edad]]<=13,"Niños",INFO_Pasajeros[[#This Row],[Edad]]<=18,"Jóvenes",INFO_Pasajeros[[#This Row],[Edad]]<=50,"Adultos",INFO_Pasajeros[[#This Row],[Edad]]>=51,"Adultos Mayores")} -> Jóvenes
A15: Bonnell, Miss. Elizabeth | B15: female | C15: 12 | D15: 22 | E15: 0 | F15: 0 | G15: 1 | H15: 1 | I15: 2620 | J15: 26.55 | K15: Desconocido | L15: C | M15: {=_xlfn.IFS(INFO_Pasajeros[[#This Row],[Edad]]<=13,"Niños",INFO_Pasajeros[[#This Row],[Edad]]<=18,"Jóvenes",INFO_Pasajeros[[#This Row],[Edad]]<=50,"Adultos",INFO_Pasajeros[[#This Row],[Edad]]>=51,"Adultos Mayores")} -> Adultos
... A664: Frauenthal, Dr. Henry William | B664: male | C664: 661 | D664: 2 | E664: 0 | F664: 2 | G664: 1 | H664: 1 | I664: 3101298 | J664: 133.65 | K664: Desconocido | L664: S | M664: {=_xlfn.IFS(INFO_Pasajeros[[#This Row],[Edad]]<=13,"Niños",INFO_Pasajeros[[#This Row],[Edad]]<=18,"Jóvenes",INFO_Pasajeros[[#This Row],[Edad]]<=50,"Adultos",INFO_Pasajeros[[#This Row],[Edad]]>=51,"Adultos Mayores")} -> Niños
A665: Badt, Mr. Mohamed | B665: male | C665: 662 | D665: 21 | E665: 0 | F665: 0 | G665: 3 | H665: 0 | I665: A./5. 2152 | J665: 7.225 | K665: Desconocido | L665: S | M665: {=_xlfn.IFS(INFO_Pasajeros[[#This Row],[Edad]]<=13,"Niños",INFO_Pasajeros[[#This Row],[Edad]]<=18,"Jóvenes",INFO_Pasajeros[[#This Row],[Edad]]<=50,"Adultos",INFO_Pasajeros[[#This Row],[Edad]]>=51,"Adultos Mayores")} -> Adultos
A666: Colley, Mr. Edward Pomeroy | B666: male | C666: 663 | D666: 56 | E666: 0 | F666: 0 | G666: 1 | H666: 0 | I666: A./5. 3235 | J666: 255.875 | K666: Desconocido | L666: S | M666: {=_xlfn.IFS(INFO_Pasajeros[[#This Row],[Edad]]<=13,"Niños",INFO_Pasajeros[[#This Row],[Edad]]<=18,"Jóvenes",INFO_Pasajeros[[#This Row],[Edad]]<=50,"Adultos",INFO_Pasajeros[[#This Row],[Edad]]>=51,"Adultos Mayores")} -> Adultos Mayores
A667: Coleff, Mr. Peju | B667: male | C667: 664 | D667: 56 | E667: 0 | F667: 0 | G667: 3 | H667: 0 | I667: A.5. 11206 | J667: 74.958 | K667: Desconocido | L667: S | M667: {=_xlfn.IFS(INFO_Pasajeros[[#This Row],[Edad]]<=13,"Niños",INFO_Pasajeros[[#This Row],[Edad]]<=18,"Jóvenes",INFO_Pasajeros[[#This Row],[Edad]]<=50,"Adultos",INFO_Pasajeros[[#This Row],[Edad]]>=51,"Adultos Mayores")} -> Adultos Mayores
A668: Lindqvist, Mr. Eino William | B668: male | C668: 665 | D668: 30 | E668: 0 | F668: 1 | G668: 3 | H668: 1 | I668: A.5. 18509 | J668: 7.925 | K668: Desconocido | L668: S | M668: {=_xlfn.IFS(INFO_Pasajeros[[#This Row],[Edad]]<=13,"Niños",INFO_Pasajeros[[#This Row],[Edad]]<=18,"Jóvenes",INFO_Pasajeros[[#This Row],[Edad]]<=50,"Adultos",INFO_Pasajeros[[#This Row],[Edad]]>=51,"Adultos Mayores")} -> Adultos
A669: Hickman, Mr. Lewis | B669: male | C669: 666 | D669: 21 | E669: 0 | F669: 2 | G669: 2 | H669: 0 | I669: A/4 45380 | J669: 73.5 | K669: Desconocido | L669: S | M669: {=_xlfn.IFS(INFO_Pasajeros[[#This Row],[Edad]]<=13,"Niños",INFO_Pasajeros[[#This Row],[Edad]]<=18,"Jóvenes",INFO_Pasajeros[[#This Row],[Edad]]<=50,"Adultos",INFO_Pasajeros[[#This Row],[Edad]]>=51,"Adultos Mayores")} -> Adultos
A670: Butler, Mr. Reginald Fenton | B670: male | C670: 667 | D670: 24 | E670: 0 | F670: 0 | G670: 2 | H670: 0 | I670: A/4 48871 | J670: 13 | K670: Desconocido | L670: S | M670: {=_xlfn.IFS(INFO_Pasajeros[[#This Row],[Edad]]<=13,"Niños",INFO_Pasajeros[[#This Row],[Edad]]<=18,"Jóvenes",INFO_Pasajeros[[#This Row],[Edad]]<=50,"Adultos",INFO_Pasajeros[[#This Row],[Edad]]>=51,"Adultos Mayores")} -> Adultos
A671: Rommetvedt, Mr. Knud Paust | B671: male | C671: 668 | D671: 39 | E671: 0 | F671: 0 | G671: 3 | H671: 0 | I671: A/4 48871 | J671: 7.775 | K671: Desconocido | L671: S | M671: {=_xlfn.IFS(INFO_Pasajeros[[#This Row],[Edad]]<=13,"Niños",INFO_Pasajeros[[#This Row],[Edad]]<=18,"Jóvenes",INFO_Pasajeros[[#This Row],[Edad]]<=50,"Adultos",INFO_Pasajeros[[#This Row],[Edad]]>=51,"Adultos Mayores")} -> Adultos
A672: Cook, Mr. Jacob | B672: male | C672: 669 | D672: 16 | E672: 0 | F672: 0 | G672: 3 | H672: 0 | I672: A/4. 20589 | J672: 8.05 | K672: Desconocido | L672: S | M672: {=_xlfn.IFS(INFO_Pasajeros[[#This Row],[Edad]]<=13,"Niños",INFO_Pasajeros[[#This Row],[Edad]]<=18,"Jóvenes",INFO_Pasajeros[[#This Row],[Edad]]<=50,"Adultos",INFO_Pasajeros[[#This Row],[Edad]]>=51,"Adultos Mayores")} -> Jóvenes
A673: Taylor, Mrs. Elmer Zebley (Juliet Cummins Wright) | B673: female | C673: 670 | D673: 20 | E673: 0 | F673: 1 | G673: 1 | H673: 1 | I673: A/4. 34244 | J673: 52 | K673: Desconocido | L673: S | M673: {=_xlfn.IFS(INFO_Pasajeros[[#This Row],[Edad]]<=13,"Niños",INFO_Pasajeros[[#This Row],[Edad]]<=18,"Jóvenes",INFO_Pasajeros[[#This Row],[Edad]]<=50,"Adultos",INFO_Pasajeros[[#This Row],[Edad]]>=51,"Adultos Mayores")} -> Adultos
A674: Brown, Mrs. Thomas William Solomon (Elizabeth Catherine Ford) | B674: female | C674: 671 | D674: 21 | E674: 1 | F674: 1 | G674: 2 | H674: 1 | I674: A/4. 39886 | J674: 39 | K674: Desconocido | L674: S | M674: {=_xlfn.IFS(INFO_Pasajeros[[#This Row],[Edad]]<=13,"Niños",INFO_Pasajeros[[#This Row],[Edad]]<=18,"Jóvenes",INFO_Pasajeros[[#This Row],[Edad]]<=50,"Adultos",INFO_Pasajeros[[#This Row],[Edad]]>=51,"Adultos Mayores")} -> Adultos
A675: Davidson, Mr. Thornton | B675: male | C675: 672 | D675: 22 | E675: 0 | F675: 1 | G675: 1 | H675: 0 | I675: A/5 21171 | J675: 52 | K675: Desconocido | L675: S | M675: {=_xlfn.IFS(INFO_Pasajeros[[#This Row],[Edad]]<=13,"Niños",INFO_Pasajeros[[#This Row],[Edad]]<=18,"Jóvenes",INFO_Pasajeros[[#This Row],[Edad]]<=50,"Adultos",INFO_Pasajeros[[#This Row],[Edad]]>=51,"Adultos Mayores")} -> Adultos
A676: Mitchell, Mr. Henry Michael | B676: male | C676: 673 | D676: 22 | E676: 0 | F676: 0 | G676: 2 | H676: 0 | I676: A/5 21172 | J676: 10.5 | K676: Desconocido | L676: S | M676: {=_xlfn.IFS(INFO_Pasajeros[[#This Row],[Edad]]<=13,"Niños",INFO_Pasajeros[[#This Row],[Edad]]<=18,"Jóvenes",INFO_Pasajeros[[#This Row],[Edad]]<=50,"Adultos",INFO_Pasajeros[[#This Row],[Edad]]>=51,"Adultos Mayores")} -> Adultos
... A894: Dooley, Mr. Patrick | B894: male | C894: 891 | D894: 70 | E894: 0 | F894: 0 | G894: 3 | H894: 0 | I894: WE/P 5735 | J894: 7.75 | K894: B22 | L894: S | M894: {=_xlfn.IFS(INFO_Pasajeros[[#This Row],[Edad]]<=13,"Niños",INFO_Pasajeros[[#This Row],[Edad]]<=18,"Jóvenes",INFO_Pasajeros[[#This Row],[Edad]]<=50,"Adultos",INFO_Pasajeros[[#This Row],[Edad]]>=51,"Adultos Mayores")} -> Adultos Mayores

Sheet Preguntas y Respuestas
A3: 1a).¿Cuántos Pasajeros había en total en el barco?, ¿Cuántos de ellos eran hombres y cuántos mujeres?.b)¿Qué porcentaje de cada uno hay respecto al total? | G3: RESPUESTA:a) El total de pasajeros registrador es de 891. De ellos 314 son mujeres y 577 son hombres.
A4: a) | B4: TOTAL | C4: SOBREVIVIENTES | D4: NO SOBREVIVIENTES | G4: Se observa mayor proporción de masculinos.
A5: Hombres: | B5: =COUNTIF(DATASET_CLEAN!B:B,"male") -> 577 | C5: =COUNTIFS(INFO_Pasajeros[Sexo],"male",INFO_Pasajeros[Sobreviviente],1) -> 109 | D5: =C5+C6 -> 342
A6: Mujeres: | B6: =COUNTIF(DATASET_CLEAN!B:B,"female") -> 314 | C6: =COUNTIFS(INFO_Pasajeros[Sexo],"female",INFO_Pasajeros[Sobreviviente],1) -> 233
A7: Total Pasajeros: | B7: =COUNTA(INFO_Pasajeros[Sexo]) -> 891
A8: b) | F8: RESPUESTA:b) Los hombres representan aproximadamente 65% del total. Mientras que las mujeres un 35%.
A9: Hombres: | B9: =COUNTIF(INFO_Pasajeros[Sexo],"male")/COUNTA(INFO_Pasajeros[Sexo]) -> 0.64758698 | C9: =ROUNDUP(B9,2) -> 0.65 | G9: Evidenciando una composición mayoritariamente masculina
A10: Mujeres: | B10: =COUNTIF(INFO_Pasajeros[Sexo],"female")/COUNTA(INFO_Pasajeros[Sexo]) -> 0.35241302 | C10: =ROUNDDOWN(B10,2) -> 0.35
A12: 2a).¿Existen diferencias en la edad promedio entre los pasarejos que sobrevivieron y los que no sobrevivieron? | F12: RESPUESTA a: La diferencia de edad promedio en ambos grupos es mínima lo que suguiere que la edad
G13: en términos generales, no fue un factor determinante por sí sola en la supervivencia.
A14: Edad Promedio: | B14: =AVERAGE(INFO_Pasajeros[Edad]) -> 31.937149 | C14: =ROUNDUP(B14,0) -> 32
A15: Edad Promedio Sobrevivientes: | B15: =AVERAGEIF(INFO_Pasajeros[Sobreviviente],1,INFO_Pasajeros[Edad]) -> 31.491228 | C15: =ROUNDDOWN(B15,1) -> 31.4
A16: Edad Promedio No Sobrevivientes: | B16: =AVERAGEIF(INFO_Pasajeros[Sobreviviente],0,INFO_Pasajeros[Edad]) -> 32.214936 | C16: =ROUNDDOWN(B16,1) -> 32.2
A18: 2b).Dado que la diferencia en la edad promedio entre sobrevivientes y no sobrevivientes es mínima, ¿Existen diferencias en la tasa de supervivencia al analizar la edad por rangos etarios? | H18: RESPUESTA b: Al segmentar por rangos de edad se observan variaciones en la tasa de supervivencia
I19: especialmente en determinados grupos etarios. Lo que indica que el análisis
A20: Rango etario | B20: TOTAL | C20: Sobrevivientes. | D20: No Sobrevivientes. | E20: Tasa de Supervivencia(%) | I20: por promedio general oculta diferencias internas relevantes
A21: Niños(0—12)): | B21: =COUNTIFS(INFO_Pasajeros[Edad],">=1",INFO_Pasajeros[Edad],"<=12") -> 96 | C21: =COUNTIFS(INFO_Pasajeros[Sobreviviente],"1",INFO_Pasajeros[Edad],">=0",INFO_Pasajeros[Edad],"<=12") -> 41 | D21: =B21-C21 -> 55 | E21: =C21/B21 -> 0.42708333
A22: Jóvenes(13—18): | B22: =COUNTIFS(INFO_Pasajeros[Edad],">=13",INFO_Pasajeros[Edad],"<=18") -> 75 | C22: =COUNTIFS(INFO_Pasajeros[Sobreviviente],"1",INFO_Pasajeros[Edad],">=13",INFO_Pasajeros[Edad],"<=18") -> 26 | D22: =B22-C22 -> 49 | E22: =C22/B22 -> 0.34666667
A23: Adultos(19—50): | B23: =COUNTIFS(INFO_Pasajeros[Edad],">=19",INFO_Pasajeros[Edad],"<=50") -> 593 | C23: =COUNTIFS(INFO_Pasajeros[Sobreviviente],"1",INFO_Pasajeros[Edad],">=19",INFO_Pasajeros[Edad],"<=50") -> 236 | D23: =B23-C23 -> 357 | E23: =C23/B23 -> 0.39797639
A24: Adultos Mayores(51+): | B24: =COUNTIF(INFO_Pasajeros[Edad],">=51") -> 127 | C24: =COUNTIFS(INFO_Pasajeros[Sobreviviente],"1",INFO_Pasajeros[Edad],">=51") -> 39 | D24: =B24-C24 -> 88 | E24: =C24/B24 -> 0.30708661
A27: 3.Tomando como ejemplo al pasajero "DeWitt Bukater, Miss. Rose", Mostrar:
A28: a)¿Qué clase de pasaje tenía?
A29: b)¿Sobrevivió?
B32: c) | C32: b) | D32: a)
B33: Nombre | C33: Sobrevivió | D33: Clase_De_Pasaje
A34: DeWitt Bukater, Miss. Rose | B34: {=CONCATENATE("Pasajero ",A34," de clase ",_xlfn.XLOOKUP(A34,INFO_Pasajeros[Nombre],INFO_Pasajeros[Clase_Del_Pasaje])," ",IF(_xlfn.XLOOKUP(A34,INFO_Pasajeros[Nombre],INFO_Pasajeros[Sobreviviente]=1),"Sobrevivió","No Sobrevivió"))} -> Pasajero DeWitt Bukater, Miss. Rose de clase 1 Sobrevivió | C34: {=IF(_xlfn.XLOOKUP('Preguntas y Respuestas'!A34,INFO_Pasajeros[Nombre],INFO_Pasajeros[Sobreviviente]=1),"Sobrevivió","No sobrevivió")} -> Sobrevivió | D34: =_xlfn.XLOOKUP(A34,INFO_Pasajeros[Nombre],INFO_Pasajeros[Clase_Del_Pasaje]) -> 1
A39: 4a)En cuestión de Tipos de pasaje. Teníamos Clase 1. Clase 2 Clase 3. ¿Cuántos había de cada uno? | F39: RESPUESTA a: La clase 3 concentra mayor cantidad de pasarejos, seguida por la clase 1 y luego la fclase 3. Lo que suguiere
F40: una relación directa entre categoría de pasaje y probabildiad de supervivencia.
A41: b)¿Cuántos tripulantes de cada clase lograron sobrevivir? | F41: RESPUESTA b: La tasa de supervivencia es significativamente mayor en la Clase 1 en comparación con las Clases 2 y 3.
F42: Lo que suigiere una relación directa entre categoría de pasaje y posibilidad de supervivencia.
A43: c)¿Qué porcentaje de cada uno nos da? | F43: RESPUESTA c: En todas las clases de observa una mayor tasa de supervivencia femenina en comparación con la masculina.
G44: Esto refuerza el patron general de priorización por sexo.
A45: a.
A46: Tipos de Pasaje | B46: Clase 1 | C46: Clase 2 | D46: Clase 3
A47: Cantidad | B47: =COUNTIF(INFO_Pasajeros[Clase_Del_Pasaje],"1") -> 216 | C47: =COUNTIF(INFO_Pasajeros[Clase_Del_Pasaje],2) -> 184 | D47: =COUNTIF(INFO_Pasajeros[Clase_Del_Pasaje],3) -> 491
A48: b.
A49: Sobrevivientes por Clase | B49: =COUNTIFS(INFO_Pasajeros[Clase_Del_Pasaje],1,INFO_Pasajeros[Sobreviviente],1) -> 136 | C49: =COUNTIFS(INFO_Pasajeros[Clase_Del_Pasaje],2,INFO_Pasajeros[Sobreviviente],1) -> 87 | D49: =COUNTIFS(INFO_Pasajeros[Clase_Del_Pasaje],3,INFO_Pasajeros[Sobreviviente],1) -> 119
A50: c.
A51: Porcentaje de sobrevivientes | B51: =B49/B47 -> 0.62962963 | C51: =C49/C47 -> 0.47282609 | D51: =D49/D47 -> 0.24236253
A54: 5.Dentro de cada Clase.¿Cuál es la tasa de supervivencia según el sexo? | F54: RESPUESTA: La tasa de supervivencia según el sexo, tiene mucha amplitud en torno al grupo femenino. Esto se debe a la priorización
G55: por se xo, que se tuvo en el momento del accidente y de decidir quienes iban primero camino a la supervivencia.
G56: Observando que las mujeres en las Clases 1 y 2 lograron una mayoría de mas del 90% y las de la Clase 3 50%.
G57: Siendo que los hombres tienen porcentajes BAJISIMOS. Teniendo en cuenta la Clase 1 que si tenia prioridad debido a su Status
A58: Clase de Pasaje | B58: Mujeres | C58: Hombres | D58: Sobrevivientes por Clase | E58: Mujeres | F58: Hombres | G58: Tasa de supervivencia | H58: Mujeres | I58: Hombres
A59: Clase 1 | B59: =COUNTIFS(INFO_Pasajeros[Sexo],"female",INFO_Pasajeros[Clase_Del_Pasaje],1) -> 94 | C59: =COUNTIFS(INFO_Pasajeros[Sexo],"male",INFO_Pasajeros[Clase_Del_Pasaje],1) -> 122 | E59: =COUNTIFS(INFO_Pasajeros[Sexo],"female",INFO_Pasajeros[Clase_Del_Pasaje],1,INFO_Pasajeros[Sobreviviente],1) -> 91 | F59: =COUNTIFS(INFO_Pasajeros[Sexo],"male",INFO_Pasajeros[Clase_Del_Pasaje],1,INFO_Pasajeros[Sobreviviente],1) -> 45 | H59: =E59/B59 -> 0.96808511 | I59: =F59/C59 -> 0.36885246
A60: Clase 2 | B60: =COUNTIFS(INFO_Pasajeros[Sexo],"female",INFO_Pasajeros[Clase_Del_Pasaje],2) -> 76 | C60: =COUNTIFS(INFO_Pasajeros[Sexo],"male",INFO_Pasajeros[Clase_Del_Pasaje],2) -> 108 | E60: =COUNTIFS(INFO_Pasajeros[Sexo],"female",INFO_Pasajeros[Clase_Del_Pasaje],2,INFO_Pasajeros[Sobreviviente],1) -> 70 | F60: =COUNTIFS(INFO_Pasajeros[Sexo],"male",INFO_Pasajeros[Clase_Del_Pasaje],2,INFO_Pasajeros[Sobreviviente],1) -> 17 | H60: =E60/B60 -> 0.92105263 | I60: =F60/C60 -> 0.15740741
A61: Clase 3 | B61: =COUNTIFS(INFO_Pasajeros[Sexo],"female",INFO_Pasajeros[Clase_Del_Pasaje],3) -> 144 | C61: =COUNTIFS(INFO_Pasajeros[Sexo],"male",INFO_Pasajeros[Clase_Del_Pasaje],3) -> 347 | E61: =COUNTIFS(INFO_Pasajeros[Sexo],"female",INFO_Pasajeros[Clase_Del_Pasaje],3,INFO_Pasajeros[Sobreviviente],1) -> 72 | F61: =COUNTIFS(INFO_Pasajeros[Sexo],"male",INFO_Pasajeros[Clase_Del_Pasaje],3,INFO_Pasajeros[Sobreviviente],1) -> 47 | H61: =E61/B61 -> 0.5 | I61: =F61/C61 -> 0.13544669
A63: TOTAL | B63: =SUM(B59,B60,B61) -> 314 | C63: =SUM(C59,C60,C61) -> 577 | E63: =SUM(E59,E60,E61) -> 233 | F63: =SUM(F59,F60,F61) -> 109 | H63: =E63/B63 -> 0.74203822 | I63: =F63/C63 -> 0.18890815
A66: 6.¿Cuál es el promedio de pago de tarifa en cada clase? | F66: RESPUESTA: La clase 1 presenta un promedio de tarifa considerablemente superior al de las Clases 2 y 3.
A67: Clase 1 | B67: =AVERAGEIF(INFO_Pasajeros[Clase_Del_Pasaje],1,INFO_Pasajeros[Tarifa]) -> 218.49202 | F67: Reflejando diferencias marcadas en el nivel socioeconómico de los pasajeros.
A68: Clase 2 | B68: =AVERAGEIF(INFO_Pasajeros[Clase_Del_Pasaje],2,INFO_Pasajeros[Tarifa]) -> 37.447511
A69: Clase 3 | B69: =AVERAGEIF(INFO_Pasajeros[Clase_Del_Pasaje],3,INFO_Pasajeros[Tarifa]) -> 61.049187
A73: 7.¿Cuál es la tarifa máxima pagada en cada clase y qué indica esto sobre distribución de precios? | F73: RESPUESTA: La clase 1 registra la tarifa más elevada. Sin embargo la presencia de valores altos en otras clases sugiere cierta
A74: Tarifa Max Clase 1 | B74: =_xlfn.MAXIFS(INFO_Pasajeros[Tarifa],INFO_Pasajeros[Clase_Del_Pasaje],1) -> 910.792 | F74: Dispersión en la distribución de precios y posibles valores atipicos.
A75: Tarifa Max Clase 2 | B75: =_xlfn.MAXIFS(INFO_Pasajeros[Tarifa],INFO_Pasajeros[Clase_Del_Pasaje],2) -> 415.792
A76: Tarifa Max Clase 3 | B76: =_xlfn.MAXIFS(INFO_Pasajeros[Tarifa],INFO_Pasajeros[Clase_Del_Pasaje],3) -> 564.958

Sheet AUXILIAR
A3: VALIDACIONES | D3: Total Tripulantes | E3: Total Sobrevivientes | F3: Etiquetas de fila | G3: Cuenta de Clase_Del_Pasaje | I3: Clase de Pasaje | J3: Sobrevivientes | L3: Cuenta de Sobreviviente | M3: Etiquetas de columna
A4: Lista_Sexo | B4: Lista_Embarque | D4: =COUNT(INFO_Pasajeros[ID_Pasajero]) -> 891 | E4: 109 | F4: 1 | G4: 122 | I4: 1 | J4: 45 | L4: Embarque | M4: Fallecidos | N4: Sobrevivientes | O4: Total general
A5: male | B5: S | D5: =COUNTIF(INFO_Pasajeros[Sexo],"male") -> 577 | E5: ='Preguntas y Respuestas'!C5 -> 109 | F5: 2 | G5: 108 | I5: 2 | J5: 17 | L5: C | M5: 86 | N5: 22 | O5: 108
A6: female | B6: C | D6: =COUNTIF(INFO_Pasajeros[Sexo],"female") -> 314 | E6: ='Preguntas y Respuestas'!C6 -> 233 | F6: 3 | G6: 347 | I6: 3 | J6: 47 | L6: Q | M6: 40 | N6: 8 | O6: 48
B7: Q | F7: Total general | G7: 577 | I7: Total general | J7: 109 | L7: S | M7: 342 | N7: 79 | O7: 421
L8: Total general | M8: 468 | N8: 109 | O8: 577
A9: Adición de pasajero
A10: DeWitt Bukater, Miss. Rose
A11: Tarifa_Max | B11: Total_Clase | C11: Mediana_X_Clas | E11: Clase | F11: Tripulantes
A12: Clase 1 | B12: =_xlfn.MAXIFS(INFO_Pasajeros[Tarifa],INFO_Pasajeros[Clase_Del_Pasaje],1) -> 910.792 | C12: {=MEDIAN(_xlfn._xlws.FILTER(INFO_Pasajeros[Tarifa],INFO_Pasajeros[Clase_Del_Pasaje]=1))} -> 107.6625 | E12: Clase 1 | F12: =COUNTIF(INFO_Pasajeros[Clase_Del_Pasaje],1) -> 216 | L12: Etiquetas de fila | M12: Suma de Sobreviviente
A13: Clase 2 | B13: =_xlfn.MAXIFS(INFO_Pasajeros[Tarifa],INFO_Pasajeros[Clase_Del_Pasaje],2) -> 415.792 | C13: {=MEDIAN(_xlfn._xlws.FILTER(INFO_Pasajeros[Tarifa],INFO_Pasajeros[Clase_Del_Pasaje]=2))} -> 15.025 | E13: Clase 2 | F13: =COUNTIF(INFO_Pasajeros[Clase_Del_Pasaje],2) -> 184 | L13: Adultos
A14: Clase 3 | B14: =_xlfn.MAXIFS(INFO_Pasajeros[Tarifa],INFO_Pasajeros[Clase_Del_Pasaje],3) -> 564.958 | C14: =MEDIAN(_xlfn._xlws.FILTER(INFO_Pasajeros[Tarifa],INFO_Pasajeros[Clase_Del_Pasaje],3)) -> 29.125 | E14: Clase 3 | F14: =COUNTIF(INFO_Pasajeros[Clase_Del_Pasaje],3) -> 491 | L14: 1 | M14: 94
L15: 2 | M15: 58
G16: Rango Etario | H16: Sobrevivientes | L16: 3 | M16: 84
G17: Edad | H17: No | I17: Si | J17: Total general | L17: Adultos Mayores
G18: 0-9 | H18: 39 | I18: 12 | J18: 51 | L18: 1 | M18: 15
G19: 10-19 | H19: 59 | I19: 15 | J19: 74 | L19: 2 | M19: 10
G20: 20-29 | H20: 135 | I20: 29 | J20: 164 | L20: 3 | M20: 14
G21: 30-39 | H21: 98 | I21: 23 | J21: 121 | L21: Jóvenes
A22: Etiquetas de fila | B22: Promedio de Sobreviviente | D22: Clase | E22: Promedio de Tarifa | G22: 40-49 | H22: 59 | I22: 10 | J22: 69 | L22: 1 | M22: 11
A23: Hombres | B23: 0.18890815 | D23: 1 | E23: 184.12961 | G23: 50-59 | H23: 39 | I23: 11 | J23: 50 | L23: 2 | M23: 7
A24: Total general | B24: 0.18890815 | D24: 2 | E24: 36.599074 | G24: 60-69 | H24: 22 | I24: 6 | J24: 28 | L24: 3 | M24: 7
D25: 3 | E25: 59.090389 | G25: 70-80 | H25: 17 | I25: 3 | J25: 20 | L25: Niños
D26: Promedio General | E26: 81.318679 | G26: Total general | H26: 468 | I26: 109 | J26: 577 | L26: 1 | M26: 16
L27: 2 | M27: 12
L28: 3 | M28: 14
A29: FALLECIDOS | L29: Total general | M29: 342
A30: =COUNTIF(INFO_Pasajeros[Sobreviviente],0) -> 549

Sheet Chequeo_Fare
A1: Fare correción 3 | B1: Fare correción 2 | C1: Fare corrección | D1: Fare
A2: =IF(Tabla3[[#This Row],[Fare correción 2]]>=1000,Tabla3[[#This Row],[Fare correción 2]]/10,Tabla3[[#This Row],[Fare correción 2]]) -> 7.25 | B2: =IF(Tabla3[[#This Row],[Fare corrección]]>1000,Tabla3[[#This Row],[Fare corrección]]/1000,Tabla3[[#This Row],[Fare corrección]]) -> 7.25 | C2: =IF(ISNUMBER(Tabla3[[#This Row],[Fare]]),Tabla3[[#This Row],[Fare]],VALUE(SUBSTITUTE(Tabla3[[#This Row],[Fare]],".",","))) -> 7.25 | D2: 7.25
A3: =IF(Tabla3[[#This Row],[Fare correción 2]]>=1000,Tabla3[[#This Row],[Fare correción 2]]/10,Tabla3[[#This Row],[Fare correción 2]]) -> 712.833 | B3: =IF(Tabla3[[#This Row],[Fare corrección]]>1000,Tabla3[[#This Row],[Fare corrección]]/1000,Tabla3[[#This Row],[Fare corrección]]) -> 712.833 | C3: =IF(ISNUMBER(Tabla3[[#This Row],[Fare]]),Tabla3[[#This Row],[Fare]],VALUE(SUBSTITUTE(Tabla3[[#This Row],[Fare]],".",","))) -> 712833 | D3: 712833 | E3: (=MAX FC2) | F3: =MAX(Tabla3[Fare correción 2]) -> 5123.292
A4: =IF(Tabla3[[#This Row],[Fare correción 2]]>=1000,Tabla3[[#This Row],[Fare correción 2]]/10,Tabla3[[#This Row],[Fare correción 2]]) -> 7.925 | B4: =IF(Tabla3[[#This Row],[Fare corrección]]>1000,Tabla3[[#This Row],[Fare corrección]]/1000,Tabla3[[#This Row],[Fare corrección]]) -> 7.925 | C4: =IF(ISNUMBER(Tabla3[[#This Row],[Fare]]),Tabla3[[#This Row],[Fare]],VALUE(SUBSTITUTE(Tabla3[[#This Row],[Fare]],".",","))) -> 7925 | D4: 7925 | E4: (MAX FC3) | F4: =MAX(Tabla3[Fare correción 3]) -> 910.792
A5: =IF(Tabla3[[#This Row],[Fare correción 2]]>=1000,Tabla3[[#This Row],[Fare correción 2]]/10,Tabla3[[#This Row],[Fare correción 2]]) -> 53.1 | B5: =IF(Tabla3[[#This Row],[Fare corrección]]>1000,Tabla3[[#This Row],[Fare corrección]]/1000,Tabla3[[#This Row],[Fare corrección]]) -> 53.1 | C5: =IF(ISNUMBER(Tabla3[[#This Row],[Fare]]),Tabla3[[#This Row],[Fare]],VALUE(SUBSTITUTE(Tabla3[[#This Row],[Fare]],".",","))) -> 53.1 | D5: 53.1
A6: =IF(Tabla3[[#This Row],[Fare correción 2]]>=1000,Tabla3[[#This Row],[Fare correción 2]]/10,Tabla3[[#This Row],[Fare correción 2]]) -> 8.05 | B6: =IF(Tabla3[[#This Row],[Fare corrección]]>1000,Tabla3[[#This Row],[Fare corrección]]/1000,Tabla3[[#This Row],[Fare corrección]]) -> 8.05 | C6: =IF(ISNUMBER(Tabla3[[#This Row],[Fare]]),Tabla3[[#This Row],[Fare]],VALUE(SUBSTITUTE(Tabla3[[#This Row],[Fare]],".",","))) -> 8.05 | D6: 8.05
A7: =IF(Tabla3[[#This Row],[Fare correción 2]]>=1000,Tabla3[[#This Row],[Fare correción 2]]/10,Tabla3[[#This Row],[Fare correción 2]]) -> 84.583 | B7: =IF(Tabla3[[#This Row],[Fare corrección]]>1000,Tabla3[[#This Row],[Fare corrección]]/1000,Tabla3[[#This Row],[Fare corrección]]) -> 84.583 | C7: =IF(ISNUMBER(Tabla3[[#This Row],[Fare]]),Tabla3[[#This Row],[Fare]],VALUE(SUBSTITUTE(Tabla3[[#This Row],[Fare]],".",","))) -> 84583 | D7: 84583
A8: =IF(Tabla3[[#This Row],[Fare correción 2]]>=1000,Tabla3[[#This Row],[Fare correción 2]]/10,Tabla3[[#This Row],[Fare correción 2]]) -> 518.625 | B8: =IF(Tabla3[[#This Row],[Fare corrección]]>1000,Tabla3[[#This Row],[Fare corrección]]/1000,Tabla3[[#This Row],[Fare corrección]]) -> 518.625 | C8: =IF(ISNUMBER(Tabla3[[#This Row],[Fare]]),Tabla3[[#This Row],[Fare]],VALUE(SUBSTITUTE(Tabla3[[#This Row],[Fare]],".",","))) -> 518625 | D8: 518625
A9: =IF(Tabla3[[#This Row],[Fare correción 2]]>=1000,Tabla3[[#This Row],[Fare correción 2]]/10,Tabla3[[#This Row],[Fare correción 2]]) -> 21.075 | B9: =IF(Tabla3[[#This Row],[Fare corrección]]>1000,Tabla3[[#This Row],[Fare corrección]]/1000,Tabla3[[#This Row],[Fare corrección]]) -> 21.075 | C9: =IF(ISNUMBER(Tabla3[[#This Row],[Fare]]),Tabla3[[#This Row],[Fare]],VALUE(SUBSTITUTE(Tabla3[[#This Row],[Fare]],".",","))) -> 21075 | D9: 21075
A10: =IF(Tabla3[[#This Row],[Fare correción 2]]>=1000,Tabla3[[#This Row],[Fare correción 2]]/10,Tabla3[[#This Row],[Fare correción 2]]) -> 111.333 | B10: =IF(Tabla3[[#This Row],[Fare corrección]]>1000,Tabla3[[#This Row],[Fare corrección]]/1000,Tabla3[[#This Row],[Fare corrección]]) -> 111.333 | C10: =IF(ISNUMBER(Tabla3[[#This Row],[Fare]]),Tabla3[[#This Row],[Fare]],VALUE(SUBSTITUTE(Tabla3[[#This Row],[Fare]],".",","))) -> 111333 | D10: 111333
A11: =IF(Tabla3[[#This Row],[Fare correción 2]]>=1000,Tabla3[[#This Row],[Fare correción 2]]/10,Tabla3[[#This Row],[Fare correción 2]]) -> 300.708 | B11: =IF(Tabla3[[#This Row],[Fare corrección]]>1000,Tabla3[[#This Row],[Fare corrección]]/1000,Tabla3[[#This Row],[Fare corrección]]) -> 300.708 | C11: =IF(ISNUMBER(Tabla3[[#This Row],[Fare]]),Tabla3[[#This Row],[Fare]],VALUE(SUBSTITUTE(Tabla3[[#This Row],[Fare]],".",","))) -> 300708 | D11: 300708
A12: =IF(Tabla3[[#This Row],[Fare correción 2]]>=1000,Tabla3[[#This Row],[Fare correción 2]]/10,Tabla3[[#This Row],[Fare correción 2]]) -> 16.7 | B12: =IF(Tabla3[[#This Row],[Fare corrección]]>1000,Tabla3[[#This Row],[Fare corrección]]/1000,Tabla3[[#This Row],[Fare corrección]]) -> 16.7 | C12: =IF(ISNUMBER(Tabla3[[#This Row],[Fare]]),Tabla3[[#This Row],[Fare]],VALUE(SUBSTITUTE(Tabla3[[#This Row],[Fare]],".",","))) -> 16.7 | D12: 16.7
A13: =IF(Tabla3[[#This Row],[Fare correción 2]]>=1000,Tabla3[[#This Row],[Fare correción 2]]/10,Tabla3[[#This Row],[Fare correción 2]]) -> 26.55 | B13: =IF(Tabla3[[#This Row],[Fare corrección]]>1000,Tabla3[[#This Row],[Fare corrección]]/1000,Tabla3[[#This Row],[Fare corrección]]) -> 26.55 | C13: =IF(ISNUMBER(Tabla3[[#This Row],[Fare]]),Tabla3[[#This Row],[Fare]],VALUE(SUBSTITUTE(Tabla3[[#This Row],[Fare]],".",","))) -> 26.55 | D13: 26.55
A14: =IF(Tabla3[[#This Row],[Fare correción 2]]>=1000,Tabla3[[#This Row],[Fare correción 2]]/10,Tabla3[[#This Row],[Fare correción 2]]) -> 8.05 | B14: =IF(Tabla3[[#This Row],[Fare corrección]]>1000,Tabla3[[#This Row],[Fare corrección]]/1000,Tabla3[[#This Row],[Fare corrección]]) -> 8.05 | C14: =IF(ISNUMBER(Tabla3[[#This Row],[Fare]]),Tabla3[[#This Row],[Fare]],VALUE(SUBSTITUTE(Tabla3[[#This Row],[Fare]],".",","))) -> 8.05 | D14: 8.05
A15: =IF(Tabla3[[#This Row],[Fare correción 2]]>=1000,Tabla3[[#This Row],[Fare correción 2]]/10,Tabla3[[#This Row],[Fare correción 2]]) -> 31.275 | B15: =IF(Tabla3[[#This Row],[Fare corrección]]>1000,Tabla3[[#This Row],[Fare corrección]]/1000,Tabla3[[#This Row],[Fare corrección]]) -> 31.275 | C15: =IF(ISNUMBER(Tabla3[[#This Row],[Fare]]),Tabla3[[#This Row],[Fare]],VALUE(SUBSTITUTE(Tabla3[[#This Row],[Fare]],".",","))) -> 31275 | D15: 31275
A16: =IF(Tabla3[[#This Row],[Fare correción 2]]>=1000,Tabla3[[#This Row],[Fare correción 2]]/10,Tabla3[[#This Row],[Fare correción 2]]) -> 78.542 | B16: =IF(Tabla3[[#This Row],[Fare corrección]]>1000,Tabla3[[#This Row],[Fare corrección]]/1000,Tabla3[[#This Row],[Fare corrección]]) -> 78.542 | C16: =IF(ISNUMBER(Tabla3[[#This Row],[Fare]]),Tabla3[[#This Row],[Fare]],VALUE(SUBSTITUTE(Tabla3[[#This Row],[Fare]],".",","))) -> 78542 | D16: 78542
A17: =IF(Tabla3[[#This Row],[Fare correción 2]]>=1000,Tabla3[[#This Row],[Fare correción 2]]/10,Tabla3[[#This Row],[Fare correción 2]]) -> 16 | B17: =IF(Tabla3[[#This Row],[Fare corrección]]>1000,Tabla3[[#This Row],[Fare corrección]]/1000,Tabla3[[#This Row],[Fare corrección]]) -> 16 | C17: =IF(ISNUMBER(Tabla3[[#This Row],[Fare]]),Tabla3[[#This Row],[Fare]],VALUE(SUBSTITUTE(Tabla3[[#This Row],[Fare]],".",","))) -> 16 | D17: 16
A18: =IF(Tabla3[[#This Row],[Fare correción 2]]>=1000,Tabla3[[#This Row],[Fare correción 2]]/10,Tabla3[[#This Row],[Fare correción 2]]) -> 29.125 | B18: =IF(Tabla3[[#This Row],[Fare corrección]]>1000,Tabla3[[#This Row],[Fare corrección]]/1000,Tabla3[[#This Row],[Fare corrección]]) -> 29.125 | C18: =IF(ISNUMBER(Tabla3[[#This Row],[Fare]]),Tabla3[[#This Row],[Fare]],VALUE(SUBSTITUTE(Tabla3[[#This Row],[Fare]],".",","))) -> 29125 | D18: 29125
A19: =IF(Tabla3[[#This Row],[Fare correción 2]]>=1000,Tabla3[[#This Row],[Fare correción 2]]/10,Tabla3[[#This Row],[Fare correción 2]]) -> 13 | B19: =IF(Tabla3[[#This Row],[Fare corrección]]>1000,Tabla3[[#This Row],[Fare corrección]]/1000,Tabla3[[#This Row],[Fare corrección]]) -> 13 | C19: =IF(ISNUMBER(Tabla3[[#This Row],[Fare]]),Tabla3[[#This Row],[Fare]],VALUE(SUBSTITUTE(Tabla3[[#This Row],[Fare]],".",","))) -> 13 | D19: 13
A20: =IF(Tabla3[[#This Row],[Fare correción 2]]>=1000,Tabla3[[#This Row],[Fare correción 2]]/10,Tabla3[[#This Row],[Fare correción 2]]) -> 18 | B20: =IF(Tabla3[[#This Row],[Fare corrección]]>1000,Tabla3[[#This Row],[Fare corrección]]/1000,Tabla3[[#This Row],[Fare corrección]]) -> 18 | C20: =IF(ISNUMBER(Tabla3[[#This Row],[Fare]]),Tabla3[[#This Row],[Fare]],VALUE(SUBSTITUTE(Tabla3[[#This Row],[Fare]],".",","))) -> 18 | D20: 18
A21: =IF(Tabla3[[#This Row],[Fare correción 2]]>=1000,Tabla3[[#This Row],[Fare correción 2]]/10,Tabla3[[#This Row],[Fare correción 2]]) -> 7.225 | B21: =IF(Tabla3[[#This Row],[Fare corrección]]>1000,Tabla3[[#This Row],[Fare corrección]]/1000,Tabla3[[#This Row],[Fare corrección]]) -> 7.225 | C21: =IF(ISNUMBER(Tabla3[[#This Row],[Fare]]),Tabla3[[#This Row],[Fare]],VALUE(SUBSTITUTE(Tabla3[[#This Row],[Fare]],".",","))) -> 7225 | D21: 7225
A22: =IF(Tabla3[[#This Row],[Fare correción 2]]>=1000,Tabla3[[#This Row],[Fare correción 2]]/10,Tabla3[[#This Row],[Fare correción 2]]) -> 26 | B22: =IF(Tabla3[[#This Row],[Fare corrección]]>1000,Tabla3[[#This Row],[Fare corrección]]/1000,Tabla3[[#This Row],[Fare corrección]]) -> 26 | C22: =IF(ISNUMBER(Tabla3[[#This Row],[Fare]]),Tabla3[[#This Row],[Fare]],VALUE(SUBSTITUTE(Tabla3[[#This Row],[Fare]],".",","))) -> 26 | D22: 26
A23: =IF(Tabla3[[#This Row],[Fare correción 2]]>=1000,Tabla3[[#This Row],[Fare correción 2]]/10,Tabla3[[#This Row],[Fare correción 2]]) -> 13 | B23: =IF(Tabla3[[#This Row],[Fare corrección]]>1000,Tabla3[[#This Row],[Fare corrección]]/1000,Tabla3[[#This Row],[Fare corrección]]) -> 13 | C23: =IF(ISNUMBER(Tabla3[[#This Row],[Fare]]),Tabla3[[#This Row],[Fare]],VALUE(SUBSTITUTE(Tabla3[[#This Row],[Fare]],".",","))) -> 13 | D23: 13
A24: =IF(Tabla3[[#This Row],[Fare correción 2]]>=1000,Tabla3[[#This Row],[Fare correción 2]]/10,Tabla3[[#This Row],[Fare correción 2]]) -> 80.292 | B24: =IF(Tabla3[[#This Row],[Fare corrección]]>1000,Tabla3[[#This Row],[Fare corrección]]/1000,Tabla3[[#This Row],[Fare corrección]]) -> 80.292 | C24: =IF(ISNUMBER(Tabla3[[#This Row],[Fare]]),Tabla3[[#This Row],[Fare]],VALUE(SUBSTITUTE(Tabla3[[#This Row],[Fare]],".",","))) -> 80292 | D24: 80292
A25: =IF(Tabla3[[#This Row],[Fare correción 2]]>=1000,Tabla3[[#This Row],[Fare correción 2]]/10,Tabla3[[#This Row],[Fare correción 2]]) -> 35.5 | B25: =IF(Tabla3[[#This Row],[Fare corrección]]>1000,Tabla3[[#This Row],[Fare corrección]]/1000,Tabla3[[#This Row],[Fare corrección]]) -> 35.5 | C25: =IF(ISNUMBER(Tabla3[[#This Row],[Fare]]),Tabla3[[#This Row],[Fare]],VALUE(SUBSTITUTE(Tabla3[[#This Row],[Fare]],".",","))) -> 35.5 | D25: 35.5
A26: =IF(Tabla3[[#This Row],[Fare correción 2]]>=1000,Tabla3[[#This Row],[Fare correción 2]]/10,Tabla3[[#This Row],[Fare correción 2]]) -> 21.075 | B26: =IF(Tabla3[[#This Row],[Fare corrección]]>1000,Tabla3[[#This Row],[Fare corrección]]/1000,Tabla3[[#This Row],[Fare corrección]]) -> 21.075 | C26: =IF(ISNUMBER(Tabla3[[#This Row],[Fare]]),Tabla3[[#This Row],[Fare]],VALUE(SUBSTITUTE(Tabla3[[#This Row],[Fare]],".",","))) -> 21075 | D26: 21075
A27: =IF(Tabla3[[#This Row],[Fare correción 2]]>=1000,Tabla3[[#This Row],[Fare correción 2]]/10,Tabla3[[#This Row],[Fare correción 2]]) -> 313.875 | B27: =IF(Tabla3[[#This Row],[Fare corrección]]>1000,Tabla3[[#This Row],[Fare corrección]]/1000,Tabla3[[#This Row],[Fare corrección]]) -> 313.875 | C27: =IF(ISNUMBER(Tabla3[[#This Row],[Fare]]),Tabla3[[#This Row],[Fare]],VALUE(SUBSTITUTE(Tabla3[[#This Row],[Fare]],".",","))) -> 313875 | D27: 313875
A28: =IF(Tabla3[[#This Row],[Fare correción 2]]>=1000,Tabla3[[#This Row],[Fare correción 2]]/10,Tabla3[[#This Row],[Fare correción 2]]) -> 7.225 | B28: =IF(Tabla3[[#This Row],[Fare corrección]]>1000,Tabla3[[#This Row],[Fare corrección]]/1000,Tabla3[[#This Row],[Fare corrección]]) -> 7.225 | C28: =IF(ISNUMBER(Tabla3[[#This Row],[Fare]]),Tabla3[[#This Row],[Fare]],VALUE(SUBSTITUTE(Tabla3[[#This Row],[Fare]],".",","))) -> 7225 | D28: 7225
A29: =IF(Tabla3[[#This Row],[Fare correción 2]]>=1000,Tabla3[[#This Row],[Fare correción 2]]/10,Tabla3[[#This Row],[Fare correción 2]]) -> 263 | B29: =IF(Tabla3[[#This Row],[Fare corrección]]>1000,Tabla3[[#This Row],[Fare corrección]]/1000,Tabla3[[#This Row],[Fare corrección]]) -> 263 | C29: =IF(ISNUMBER(Tabla3[[#This Row],[Fare]]),Tabla3[[#This Row],[Fare]],VALUE(SUBSTITUTE(Tabla3[[#This Row],[Fare]],".",","))) -> 263 | D29: 263
A30: =IF(Tabla3[[#This Row],[Fare correción 2]]>=1000,Tabla3[[#This Row],[Fare correción 2]]/10,Tabla3[[#This Row],[Fare correción 2]]) -> 78.792 | B30: =IF(Tabla3[[#This Row],[Fare corrección]]>1000,Tabla3[[#This Row],[Fare corrección]]/1000,Tabla3[[#This Row],[Fare corrección]]) -> 78.792 | C30: =IF(ISNUMBER(Tabla3[[#This Row],[Fare]]),Tabla3[[#This Row],[Fare]],VALUE(SUBSTITUTE(Tabla3[[#This Row],[Fare]],".",","))) -> 78792 | D30: 78792
A31: =IF(Tabla3[[#This Row],[Fare correción 2]]>=1000,Tabla3[[#This Row],[Fare correción 2]]/10,Tabla3[[#This Row],[Fare correción 2]]) -> 78.958 | B31: =IF(Tabla3[[#This Row],[Fare corrección]]>1000,Tabla3[[#This Row],[Fare corrección]]/1000,Tabla3[[#This Row],[Fare corrección]]) -> 78.958 | C31: =IF(ISNUMBER(Tabla3[[#This Row],[Fare]]),Tabla3[[#This Row],[Fare]],VALUE(SUBSTITUTE(Tabla3[[#This Row],[Fare]],".",","))) -> 78958 | D31: 78958
A32: =IF(Tabla3[[#This Row],[Fare correción 2]]>=1000,Tabla3[[#This Row],[Fare correción 2]]/10,Tabla3[[#This Row],[Fare correción 2]]) -> 277.208 | B32: =IF(Tabla3[[#This Row],[Fare corrección]]>1000,Tabla3[[#This Row],[Fare corrección]]/1000,Tabla3[[#This Row],[Fare corrección]]) -> 277.208 | C32: =IF(ISNUMBER(Tabla3[[#This Row],[Fare]]),Tabla3[[#This Row],[Fare]],VALUE(SUBSTITUTE(Tabla3[[#This Row],[Fare]],".",","))) -> 277208 | D32: 277208
A33: =IF(Tabla3[[#This Row],[Fare correción 2]]>=1000,Tabla3[[#This Row],[Fare correción 2]]/10,Tabla3[[#This Row],[Fare correción 2]]) -> 146.5208 | B33: =IF(Tabla3[[#This Row],[Fare corrección]]>1000,Tabla3[[#This Row],[Fare corrección]]/1000,Tabla3[[#This Row],[Fare corrección]]) -> 1465.208 | C33: =IF(ISNUMBER(Tabla3[[#This Row],[Fare]]),Tabla3[[#This Row],[Fare]],VALUE(SUBSTITUTE(Tabla3[[#This Row],[Fare]],".",","))) -> 1465208 | D33: 1465208
A34: =IF(Tabla3[[#This Row],[Fare correción 2]]>=1000,Tabla3[[#This Row],[Fare correción 2]]/10,Tabla3[[#This Row],[Fare correción 2]]) -> 7.75 | B34: =IF(Tabla3[[#This Row],[Fare corrección]]>1000,Tabla3[[#This Row],[Fare corrección]]/1000,Tabla3[[#This Row],[Fare corrección]]) -> 7.75 | C34: =IF(ISNUMBER(Tabla3[[#This Row],[Fare]]),Tabla3[[#This Row],[Fare]],VALUE(SUBSTITUTE(Tabla3[[#This Row],[Fare]],".",","))) -> 7.75 | D34: 7.75
A35: =IF(Tabla3[[#This Row],[Fare correción 2]]>=1000,Tabla3[[#This Row],[Fare correción 2]]/10,Tabla3[[#This Row],[Fare correción 2]]) -> 10.5 | B35: =IF(Tabla3[[#This Row],[Fare corrección]]>1000,Tabla3[[#This Row],[Fare corrección]]/1000,Tabla3[[#This Row],[Fare corrección]]) -> 10.5 | C35: =IF(ISNUMBER(Tabla3[[#This Row],[Fare]]),Tabla3[[#This Row],[Fare]],VALUE(SUBSTITUTE(Tabla3[[#This Row],[Fare]],".",","))) -> 10.5 | D35: 10.5
A36: =IF(Tabla3[[#This Row],[Fare correción 2]]>=1000,Tabla3[[#This Row],[Fare correción 2]]/10,Tabla3[[#This Row],[Fare correción 2]]) -> 821.708 | B36: =IF(Tabla3[[#This Row],[Fare corrección]]>1000,Tabla3[[#This Row],[Fare corrección]]/1000,Tabla3[[#This Row],[Fare corrección]]) -> 821.708 | C36: =IF(ISNUMBER(Tabla3[[#This Row],[Fare]]),Tabla3[[#This Row],[Fare]],VALUE(SUBSTITUTE(Tabla3[[#This Row],[Fare]],".",","))) -> 821708 | D36: 821708
A37: =IF(Tabla3[[#This Row],[Fare correción 2]]>=1000,Tabla3[[#This Row],[Fare correción 2]]/10,Tabla3[[#This Row],[Fare correción 2]]) -> 52 | B37: =IF(Tabla3[[#This Row],[Fare corrección]]>1000,Tabla3[[#This Row],[Fare corrección]]/1000,Tabla3[[#This Row],[Fare corrección]]) -> 52 | C37: =IF(ISNUMBER(Tabla3[[#This Row],[Fare]]),Tabla3[[#This Row],[Fare]],VALUE(SUBSTITUTE(Tabla3[[#This Row],[Fare]],".",","))) -> 52 | D37: 52
A38: =IF(Tabla3[[#This Row],[Fare correción 2]]>=1000,Tabla3[[#This Row],[Fare correción 2]]/10,Tabla3[[#This Row],[Fare correción 2]]) -> 72.292 | B38: =IF(Tabla3[[#This Row],[Fare corrección]]>1000,Tabla3[[#This Row],[Fare corrección]]/1000,Tabla3[[#This Row],[Fare corrección]]) -> 72.292 | C38: =IF(ISNUMBER(Tabla3[[#This Row],[Fare]]),Tabla3[[#This Row],[Fare]],VALUE(SUBSTITUTE(Tabla3[[#This Row],[Fare]],".",","))) -> 72292 | D38: 72292
A39: =IF(Tabla3[[#This Row],[Fare correción 2]]>=1000,Tabla3[[#This Row],[Fare correción 2]]/10,Tabla3[[#This Row],[Fare correción 2]]) -> 8.05 | B39: =IF(Tabla3[[#This Row],[Fare corrección]]>1000,Tabla3[[#This Row],[Fare corrección]]/1000,Tabla3[[#This Row],[Fare corrección]]) -> 8.05 | C39: =IF(ISNUMBER(Tabla3[[#This Row],[Fare]]),Tabla3[[#This Row],[Fare]],VALUE(SUBSTITUTE(Tabla3[[#This Row],[Fare]],".",","))) -> 8.05 | D39: 8.05
A40: =IF(Tabla3[[#This Row],[Fare correción 2]]>=1000,Tabla3[[#This Row],[Fare correción 2]]/10,Tabla3[[#This Row],[Fare correción 2]]) -> 18 | B40: =IF(Tabla3[[#This Row],[Fare corrección]]>1000,Tabla3[[#This Row],[Fare corrección]]/1000,Tabla3[[#This Row],[Fare corrección]]) -> 18 | C40: =IF(ISNUMBER(Tabla3[[#This Row],[Fare]]),Tabla3[[#This Row],[Fare]],VALUE(SUBSTITUTE(Tabla3[[#This Row],[Fare]],".",","))) -> 18 | D40: 18
A41: =IF(Tabla3[[#This Row],[Fare correción 2]]>=1000,Tabla3[[#This Row],[Fare correción 2]]/10,Tabla3[[#This Row],[Fare correción 2]]) -> 112.417 | B41: =IF(Tabla3[[#This Row],[Fare corrección]]>1000,Tabla3[[#This Row],[Fare corrección]]/1000,Tabla3[[#This Row],[Fare corrección]]) -> 112.417 | C41: =IF(ISNUMBER(Tabla3[[#This Row],[Fare]]),Tabla3[[#This Row],[Fare]],VALUE(SUBSTITUTE(Tabla3[[#This Row],[Fare]],".",","))) -> 112417 | D41: 112417
A42: =IF(Tabla3[[#This Row],[Fare correción 2]]>=1000,Tabla3[[#This Row],[Fare correción 2]]/10,Tabla3[[#This Row],[Fare correción 2]]) -> 9.475 | B42: =IF(Tabla3[[#This Row],[Fare corrección]]>1000,Tabla3[[#This Row],[Fare corrección]]/1000,Tabla3[[#This Row],[Fare corrección]]) -> 9.475 | C42: =IF(ISNUMBER(Tabla3[[#This Row],[Fare]]),Tabla3[[#This Row],[Fare]],VALUE(SUBSTITUTE(Tabla3[[#This Row],[Fare]],".",","))) -> 9475 | D42: 9475
A43: =IF(Tabla3[[#This Row],[Fare correción 2]]>=1000,Tabla3[[#This Row],[Fare correción 2]]/10,Tabla3[[#This Row],[Fare correción 2]]) -> 21 | B43: =IF(Tabla3[[#This Row],[Fare corrección]]>1000,Tabla3[[#This Row],[Fare corrección]]/1000,Tabla3[[#This Row],[Fare corrección]]) -> 21 | C43: =IF(ISNUMBER(Tabla3[[#This Row],[Fare]]),Tabla3[[#This Row],[Fare]],VALUE(SUBSTITUTE(Tabla3[[#This Row],[Fare]],".",","))) -> 21 | D43: 21
A44: =IF(Tabla3[[#This Row],[Fare correción 2]]>=1000,Tabla3[[#This Row],[Fare correción 2]]/10,Tabla3[[#This Row],[Fare correción 2]]) -> 78.958 | B44: =IF(Tabla3[[#This Row],[Fare corrección]]>1000,Tabla3[[#This Row],[Fare corrección]]/1000,Tabla3[[#This Row],[Fare corrección]]) -> 78.958 | C44: =IF(ISNUMBER(Tabla3[[#This Row],[Fare]]),Tabla3[[#This Row],[Fare]],VALUE(SUBSTITUTE(Tabla3[[#This Row],[Fare]],".",","))) -> 78958 | D44: 78958
A45: =IF(Tabla3[[#This Row],[Fare correción 2]]>=1000,Tabla3[[#This Row],[Fare correción 2]]/10,Tabla3[[#This Row],[Fare correción 2]]) -> 415.792 | B45: =IF(Tabla3[[#This Row],[Fare corrección]]>1000,Tabla3[[#This Row],[Fare corrección]]/1000,Tabla3[[#This Row],[Fare corrección]]) -> 415.792 | C45: =IF(ISNUMBER(Tabla3[[#This Row],[Fare]]),Tabla3[[#This Row],[Fare]],VALUE(SUBSTITUTE(Tabla3[[#This Row],[Fare]],".",","))) -> 415792 | D45: 415792
A46: =IF(Tabla3[[#This Row],[Fare correción 2]]>=1000,Tabla3[[#This Row],[Fare correción 2]]/10,Tabla3[[#This Row],[Fare correción 2]]) -> 78.792 | B46: =IF(Tabla3[[#This Row],[Fare corrección]]>1000,Tabla3[[#This Row],[Fare corrección]]/1000,Tabla3[[#This Row],[Fare corrección]]) -> 78.792 | C46: =IF(ISNUMBER(Tabla3[[#This Row],[Fare]]),Tabla3[[#This Row],[Fare]],VALUE(SUBSTITUTE(Tabla3[[#This Row],[Fare]],".",","))) -> 78792 | D46: 78792
A47: =IF(Tabla3[[#This Row],[Fare correción 2]]>=1000,Tabla3[[#This Row],[Fare correción 2]]/10,Tabla3[[#This Row],[Fare correción 2]]) -> 8.05 | B47: =IF(Tabla3[[#This Row],[Fare corrección]]>1000,Tabla3[[#This Row],[Fare corrección]]/1000,Tabla3[[#This Row],[Fare corrección]]) -> 8.05 | C47: =IF(ISNUMBER(Tabla3[[#This Row],[Fare]]),Tabla3[[#This Row],[Fare]],VALUE(SUBSTITUTE(Tabla3[[#This Row],[Fare]],".",","))) -> 8.05 | D47: 8.05
A48: =IF(Tabla3[[#This Row],[Fare correción 2]]>=1000,Tabla3[[#This Row],[Fare correción 2]]/10,Tabla3[[#This Row],[Fare correción 2]]) -> 15.5 | B48: =IF(Tabla3[[#This Row],[Fare corrección]]>1000,Tabla3[[#This Row],[Fare corrección]]/1000,Tabla3[[#This Row],[Fare corrección]]) -> 15.5 | C48: =IF(ISNUMBER(Tabla3[[#This Row],[Fare]]),Tabla3[[#This Row],[Fare]],VALUE(SUBSTITUTE(Tabla3[[#This Row],[Fare]],".",","))) -> 15.5 | D48: 15.5
A49: =IF(Tabla3[[#This Row],[Fare correción 2]]>=1000,Tabla3[[#This Row],[Fare correción 2]]/10,Tabla3[[#This Row],[Fare correción 2]]) -> 7.75 | B49: =IF(Tabla3[[#This Row],[Fare corrección]]>1000,Tabla3[[#This Row],[Fare corrección]]/1000,Tabla3[[#This Row],[Fare corrección]]) -> 7.75 | C49: =IF(ISNUMBER(Tabla3[[#This Row],[Fare]]),Tabla3[[#This Row],[Fare]],VALUE(SUBSTITUTE(Tabla3[[#This Row],[Fare]],".",","))) -> 7.75 | D49: 7.75
A50: =IF(Tabla3[[#This Row],[Fare correción 2]]>=1000,Tabla3[[#This Row],[Fare correción 2]]/10,Tabla3[[#This Row],[Fare correción 2]]) -> 216.792 | B50: =IF(Tabla3[[#This Row],[Fare corrección]]>1000,Tabla3[[#This Row],[Fare corrección]]/1000,Tabla3[[#This Row],[Fare corrección]]) -> 216.792 | C50: =IF(ISNUMBER(Tabla3[[#This Row],[Fare]]),Tabla3[[#This Row],[Fare]],VALUE(SUBSTITUTE(Tabla3[[#This Row],[Fare]],".",","))) -> 216792 | D50: 216792
A51: =IF(Tabla3[[#This Row],[Fare correción 2]]>=1000,Tabla3[[#This Row],[Fare correción 2]]/10,Tabla3[[#This Row],[Fare correción 2]]) -> 17.8 | B51: =IF(Tabla3[[#This Row],[Fare corrección]]>1000,Tabla3[[#This Row],[Fare corrección]]/1000,Tabla3[[#This Row],[Fare corrección]]) -> 17.8 | C51: =IF(ISNUMBER(Tabla3[[#This Row],[Fare]]),Tabla3[[#This Row],[Fare]],VALUE(SUBSTITUTE(Tabla3[[#This Row],[Fare]],".",","))) -> 17.8 | D51: 17.8
A52: =IF(Tabla3[[#This Row],[Fare correción 2]]>=1000,Tabla3[[#This Row],[Fare correción 2]]/10,Tabla3[[#This Row],[Fare correción 2]]) -> 396.875 | B52: =IF(Tabla3[[#This Row],[Fare corrección]]>1000,Tabla3[[#This Row],[Fare corrección]]/1000,Tabla3[[#This Row],[Fare corrección]]) -> 396.875 | C52: =IF(ISNUMBER(Tabla3[[#This Row],[Fare]]),Tabla3[[#This Row],[Fare]],VALUE(SUBSTITUTE(Tabla3[[#This Row],[Fare]],".",","))) -> 396875 | D52: 396875
A53: =IF(Tabla3[[#This Row],[Fare correción 2]]>=1000,Tabla3[[#This Row],[Fare correción 2]]/10,Tabla3[[#This Row],[Fare correción 2]]) -> 7.8 | B53: =IF(Tabla3[[#This Row],[Fare corrección]]>1000,Tabla3[[#This Row],[Fare corrección]]/1000,Tabla3[[#This Row],[Fare corrección]]) -> 7.8 | C53: =IF(ISNUMBER(Tabla3[[#This Row],[Fare]]),Tabla3[[#This Row],[Fare]],VALUE(SUBSTITUTE(Tabla3[[#This Row],[Fare]],".",","))) -> 7.8 | D53: 7.8
A54: =IF(Tabla3[[#This Row],[Fare correción 2]]>=1000,Tabla3[[#This Row],[Fare correción 2]]/10,Tabla3[[#This Row],[Fare correción 2]]) -> 767.292 | B54: =IF(Tabla3[[#This Row],[Fare corrección]]>1000,Tabla3[[#This Row],[Fare corrección]]/1000,Tabla3[[#This Row],[Fare corrección]]) -> 767.292 | C54: =IF(ISNUMBER(Tabla3[[#This Row],[Fare]]),Tabla3[[#This Row],[Fare]],VALUE(SUBSTITUTE(Tabla3[[#This Row],[Fare]],".",","))) -> 767292 | D54: 767292
A55: =IF(Tabla3[[#This Row],[Fare correción 2]]>=1000,Tabla3[[#This Row],[Fare correción 2]]/10,Tabla3[[#This Row],[Fare correción 2]]) -> 26 | B55: =IF(Tabla3[[#This Row],[Fare corrección]]>1000,Tabla3[[#This Row],[Fare corrección]]/1000,Tabla3[[#This Row],[Fare corrección]]) -> 26 | C55: =IF(ISNUMBER(Tabla3[[#This Row],[Fare]]),Tabla3[[#This Row],[Fare]],VALUE(SUBSTITUTE(Tabla3[[#This Row],[Fare]],".",","))) -> 26 | D55: 26
A56: =IF(Tabla3[[#This Row],[Fare correción 2]]>=1000,Tabla3[[#This Row],[Fare correción 2]]/10,Tabla3[[#This Row],[Fare correción 2]]) -> 619.792 | B56: =IF(Tabla3[[#This Row],[Fare corrección]]>1000,Tabla3[[#This Row],[Fare corrección]]/1000,Tabla3[[#This Row],[Fare corrección]]) -> 619.792 | C56: =IF(ISNUMBER(Tabla3[[#This Row],[Fare]]),Tabla3[[#This Row],[Fare]],VALUE(SUBSTITUTE(Tabla3[[#This Row],[Fare]],".",","))) -> 619792 | D56: 619792
A57: =IF(Tabla3[[#This Row],[Fare correción 2]]>=1000,Tabla3[[#This Row],[Fare correción 2]]/10,Tabla3[[#This Row],[Fare correción 2]]) -> 35.5 | B57: =IF(Tabla3[[#This Row],[Fare corrección]]>1000,Tabla3[[#This Row],[Fare corrección]]/1000,Tabla3[[#This Row],[Fare corrección]]) -> 35.5 | C57: =IF(ISNUMBER(Tabla3[[#This Row],[Fare]]),Tabla3[[#This Row],[Fare]],VALUE(SUBSTITUTE(Tabla3[[#This Row],[Fare]],".",","))) -> 35.5 | D57: 35.5
A58: =IF(Tabla3[[#This Row],[Fare correción 2]]>=1000,Tabla3[[#This Row],[Fare correción 2]]/10,Tabla3[[#This Row],[Fare correción 2]]) -> 10.5 | B58: =IF(Tabla3[[#This Row],[Fare corrección]]>1000,Tabla3[[#This Row],[Fare corrección]]/1000,Tabla3[[#This Row],[Fare corrección]]) -> 10.5 | C58: =IF(ISNUMBER(Tabla3[[#This Row],[Fare]]),Tabla3[[#This Row],[Fare]],VALUE(SUBSTITUTE(Tabla3[[#This Row],[Fare]],".",","))) -> 10.5 | D58: 10.5
A59: =IF(Tabla3[[#This Row],[Fare correción 2]]>=1000,Tabla3[[#This Row],[Fare correción 2]]/10,Tabla3[[#This Row],[Fare correción 2]]) -> 72.292 | B59: =IF(Tabla3[[#This Row],[Fare corrección]]>1000,Tabla3[[#This Row],[Fare corrección]]/1000,Tabla3[[#This Row],[Fare corrección]]) -> 72.292 | C59: =IF(ISNUMBER(Tabla3[[#This Row],[Fare]]),Tabla3[[#This Row],[Fare]],VALUE(SUBSTITUTE(Tabla3[[#This Row],[Fare]],".",","))) -> 72292 | D59: 72292
A60: =IF(Tabla3[[#This Row],[Fare correción 2]]>=1000,Tabla3[[#This Row],[Fare correción 2]]/10,Tabla3[[#This Row],[Fare correción 2]]) -> 27.75 | B60: =IF(Tabla3[[#This Row],[Fare corrección]]>1000,Tabla3[[#This Row],[Fare corrección]]/1000,Tabla3[[#This Row],[Fare corrección]]) -> 27.75 | C60: =IF(ISNUMBER(Tabla3[[#This Row],[Fare]]),Tabla3[[#This Row],[Fare]],VALUE(SUBSTITUTE(Tabla3[[#This Row],[Fare]],".",","))) -> 27.75 | D60: 27.75
A61: =IF(Tabla3[[#This Row],[Fare correción 2]]>=1000,Tabla3[[#This Row],[Fare correción 2]]/10,Tabla3[[#This Row],[Fare correción 2]]) -> 46.9 | B61: =IF(Tabla3[[#This Row],[Fare corrección]]>1000,Tabla3[[#This Row],[Fare corrección]]/1000,Tabla3[[#This Row],[Fare corrección]]) -> 46.9 | C61: =IF(ISNUMBER(Tabla3[[#This Row],[Fare]]),Tabla3[[#This Row],[Fare]],VALUE(SUBSTITUTE(Tabla3[[#This Row],[Fare]],".",","))) -> 46.9 | D61: 46.9
A62: =IF(Tabla3[[#This Row],[Fare correción 2]]>=1000,Tabla3[[#This Row],[Fare correción 2]]/10,Tabla3[[#This Row],[Fare correción 2]]) -> 72.292 | B62: =IF(Tabla3[[#This Row],[Fare corrección]]>1000,Tabla3[[#This Row],[Fare corrección]]/1000,Tabla3[[#This Row],[Fare corrección]]) -> 72.292 | C62: =IF(ISNUMBER(Tabla3[[#This Row],[Fare]]),Tabla3[[#This Row],[Fare]],VALUE(SUBSTITUTE(Tabla3[[#This Row],[Fare]],".",","))) -> 72292 | D62: 72292
A63: =IF(Tabla3[[#This Row],[Fare correción 2]]>=1000,Tabla3[[#This Row],[Fare correción 2]]/10,Tabla3[[#This Row],[Fare correción 2]]) -> 80 | B63: =IF(Tabla3[[#This Row],[Fare corrección]]>1000,Tabla3[[#This Row],[Fare corrección]]/1000,Tabla3[[#This Row],[Fare corrección]]) -> 80 | C63: =IF(ISNUMBER(Tabla3[[#This Row],[Fare]]),Tabla3[[#This Row],[Fare]],VALUE(SUBSTITUTE(Tabla3[[#This Row],[Fare]],".",","))) -> 80 | D63: 80
A64: =IF(Tabla3[[#This Row],[Fare correción 2]]>=1000,Tabla3[[#This Row],[Fare correción 2]]/10,Tabla3[[#This Row],[Fare correción 2]]) -> 83.475 | B64: =IF(Tabla3[[#This Row],[Fare corrección]]>1000,Tabla3[[#This Row],[Fare corrección]]/1000,Tabla3[[#This Row],[Fare corrección]]) -> 83.475 | C64: =IF(ISNUMBER(Tabla3[[#This Row],[Fare]]),Tabla3[[#This Row],[Fare]],VALUE(SUBSTITUTE(Tabla3[[#This Row],[Fare]],".",","))) -> 83475 | D64: 83475
A65: =IF(Tabla3[[#This Row],[Fare correción 2]]>=1000,Tabla3[[#This Row],[Fare correción 2]]/10,Tabla3[[#This Row],[Fare correción 2]]) -> 27.9 | B65: =IF(Tabla3[[#This Row],[Fare corrección]]>1000,Tabla3[[#This Row],[Fare corrección]]/1000,Tabla3[[#This Row],[Fare corrección]]) -> 27.9 | C65: =IF(ISNUMBER(Tabla3[[#This Row],[Fare]]),Tabla3[[#This Row],[Fare]],VALUE(SUBSTITUTE(Tabla3[[#This Row],[Fare]],".",","))) -> 27.9 | D65: 27.9
A66: =IF(Tabla3[[#This Row],[Fare correción 2]]>=1000,Tabla3[[#This Row],[Fare correción 2]]/10,Tabla3[[#This Row],[Fare correción 2]]) -> 277.208 | B66: =IF(Tabla3[[#This Row],[Fare corrección]]>1000,Tabla3[[#This Row],[Fare corrección]]/1000,Tabla3[[#This Row],[Fare corrección]]) -> 277.208 | C66: =IF(ISNUMBER(Tabla3[[#This Row],[Fare]]),Tabla3[[#This Row],[Fare]],VALUE(SUBSTITUTE(Tabla3[[#This Row],[Fare]],".",","))) -> 277208 | D66: 277208
A67: =IF(Tabla3[[#This Row],[Fare correción 2]]>=1000,Tabla3[[#This Row],[Fare correción 2]]/10,Tabla3[[#This Row],[Fare correción 2]]) -> 152.458 | B67: =IF(Tabla3[[#This Row],[Fare corrección]]>1000,Tabla3[[#This Row],[Fare corrección]]/1000,Tabla3[[#This Row],[Fare corrección]]) -> 152.458 | C67: =IF(ISNUMBER(Tabla3[[#This Row],[Fare]]),Tabla3[[#This Row],[Fare]],VALUE(SUBSTITUTE(Tabla3[[#This Row],[Fare]],".",","))) -> 152458 | D67: 152458
A68: =IF(Tabla3[[#This Row],[Fare correción 2]]>=1000,Tabla3[[#This Row],[Fare correción 2]]/10,Tabla3[[#This Row],[Fare correción 2]]) -> 10.5 | B68: =IF(Tabla3[[#This Row],[Fare corrección]]>1000,Tabla3[[#This Row],[Fare corrección]]/1000,Tabla3[[#This Row],[Fare corrección]]) -> 10.5 | C68: =IF(ISNUMBER(Tabla3[[#This Row],[Fare]]),Tabla3[[#This Row],[Fare]],VALUE(SUBSTITUTE(Tabla3[[#This Row],[Fare]],".",","))) -> 10.5 | D68: 10.5
A69: =IF(Tabla3[[#This Row],[Fare correción 2]]>=1000,Tabla3[[#This Row],[Fare correción 2]]/10,Tabla3[[#This Row],[Fare correción 2]]) -> 81.583 | B69: =IF(Tabla3[[#This Row],[Fare corrección]]>1000,Tabla3[[#This Row],[Fare corrección]]/1000,Tabla3[[#This Row],[Fare corrección]]) -> 81.583 | C69: =IF(ISNUMBER(Tabla3[[#This Row],[Fare]]),Tabla3[[#This Row],[Fare]],VALUE(SUBSTITUTE(Tabla3[[#This Row],[Fare]],".",","))) -> 81583 | D69: 81583
A70: =IF(Tabla3[[#This Row],[Fare correción 2]]>=1000,Tabla3[[#This Row],[Fare correción 2]]/10,Tabla3[[#This Row],[Fare correción 2]]) -> 7.925 | B70: =IF(Tabla3[[#This Row],[Fare corrección]]>1000,Tabla3[[#This Row],[Fare corrección]]/1000,Tabla3[[#This Row],[Fare corrección]]) -> 7.925 | C70: =IF(ISNUMBER(Tabla3[[#This Row],[Fare]]),Tabla3[[#This Row],[Fare]],VALUE(SUBSTITUTE(Tabla3[[#This Row],[Fare]],".",","))) -> 7925 | D70: 7925
A71: =IF(Tabla3[[#This Row],[Fare correción 2]]>=1000,Tabla3[[#This Row],[Fare correción 2]]/10,Tabla3[[#This Row],[Fare correción 2]]) -> 86.625 | B71: =IF(Tabla3[[#This Row],[Fare corrección]]>1000,Tabla3[[#This Row],[Fare corrección]]/1000,Tabla3[[#This Row],[Fare corrección]]) -> 86.625 | C71: =IF(ISNUMBER(Tabla3[[#This Row],[Fare]]),Tabla3[[#This Row],[Fare]],VALUE(SUBSTITUTE(Tabla3[[#This Row],[Fare]],".",","))) -> 86625 | D71: 86625
A72: =IF(Tabla3[[#This Row],[Fare correción 2]]>=1000,Tabla3[[#This Row],[Fare correción 2]]/10,Tabla3[[#This Row],[Fare correción 2]]) -> 10.5 | B72: =IF(Tabla3[[#This Row],[Fare corrección]]>1000,Tabla3[[#This Row],[Fare corrección]]/1000,Tabla3[[#This Row],[Fare corrección]]) -> 10.5 | C72: =IF(ISNUMBER(Tabla3[[#This Row],[Fare]]),Tabla3[[#This Row],[Fare]],VALUE(SUBSTITUTE(Tabla3[[#This Row],[Fare]],".",","))) -> 10.5 | D72: 10.5
A73: =IF(Tabla3[[#This Row],[Fare correción 2]]>=1000,Tabla3[[#This Row],[Fare correción 2]]/10,Tabla3[[#This Row],[Fare correción 2]]) -> 46.9 | B73: =IF(Tabla3[[#This Row],[Fare corrección]]>1000,Tabla3[[#This Row],[Fare corrección]]/1000,Tabla3[[#This Row],[Fare corrección]]) -> 46.9 | C73: =IF(ISNUMBER(Tabla3[[#This Row],[Fare]]),Tabla3[[#This Row],[Fare]],VALUE(SUBSTITUTE(Tabla3[[#This Row],[Fare]],".",","))) -> 46.9 | D73: 46.9
A74: =IF(Tabla3[[#This Row],[Fare correción 2]]>=1000,Tabla3[[#This Row],[Fare correción 2]]/10,Tabla3[[#This Row],[Fare correción 2]]) -> 73.5 | B74: =IF(Tabla3[[#This Row],[Fare corrección]]>1000,Tabla3[[#This Row],[Fare corrección]]/1000,Tabla3[[#This Row],[Fare corrección]]) -> 73.5 | C74: =IF(ISNUMBER(Tabla3[[#This Row],[Fare]]),Tabla3[[#This Row],[Fare]],VALUE(SUBSTITUTE(Tabla3[[#This Row],[Fare]],".",","))) -> 73.5 | D74: 73.5
A75: =IF(Tabla3[[#This Row],[Fare correción 2]]>=1000,Tabla3[[#This Row],[Fare correción 2]]/10,Tabla3[[#This Row],[Fare correción 2]]) -> 144.542 | B75: =IF(Tabla3[[#This Row],[Fare corrección]]>1000,Tabla3[[#This Row],[Fare corrección]]/1000,Tabla3[[#This Row],[Fare corrección]]) -> 144.542 | C75: =IF(ISNUMBER(Tabla3[[#This Row],[Fare]]),Tabla3[[#This Row],[Fare]],VALUE(SUBSTITUTE(Tabla3[[#This Row],[Fare]],".",","))) -> 144542 | D75: 144542
A76: =IF(Tabla3[[#This Row],[Fare correción 2]]>=1000,Tabla3[[#This Row],[Fare correción 2]]/10,Tabla3[[#This Row],[Fare correción 2]]) -> 564.958 | B76: =IF(Tabla3[[#This Row],[Fare corrección]]>1000,Tabla3[[#This Row],[Fare corrección]]/1000,Tabla3[[#This Row],[Fare corrección]]) -> 564.958 | C76: =IF(ISNUMBER(Tabla3[[#This Row],[Fare]]),Tabla3[[#This Row],[Fare]],VALUE(SUBSTITUTE(Tabla3[[#This Row],[Fare]],".",","))) -> 564958 | D76: 564958
A77: =IF(Tabla3[[#This Row],[Fare correción 2]]>=1000,Tabla3[[#This Row],[Fare correción 2]]/10,Tabla3[[#This Row],[Fare correción 2]]) -> 7.65 | B77: =IF(Tabla3[[#This Row],[Fare corrección]]>1000,Tabla3[[#This Row],[Fare corrección]]/1000,Tabla3[[#This Row],[Fare corrección]]) -> 7.65 | C77: =IF(ISNUMBER(Tabla3[[#This Row],[Fare]]),Tabla3[[#This Row],[Fare]],VALUE(SUBSTITUTE(Tabla3[[#This Row],[Fare]],".",","))) -> 7.65 | D77: 7.65
A78: =IF(Tabla3[[#This Row],[Fare correción 2]]>=1000,Tabla3[[#This Row],[Fare correción 2]]/10,Tabla3[[#This Row],[Fare correción 2]]) -> 78.958 | B78: =IF(Tabla3[[#This Row],[Fare corrección]]>1000,Tabla3[[#This Row],[Fare corrección]]/1000,Tabla3[[#This Row],[Fare corrección]]) -> 78.958 | C78: =IF(ISNUMBER(Tabla3[[#This Row],[Fare]]),Tabla3[[#This Row],[Fare]],VALUE(SUBSTITUTE(Tabla3[[#This Row],[Fare]],".",","))) -> 78958 | D78: 78958
A79: =IF(Tabla3[[#This Row],[Fare correción 2]]>=1000,Tabla3[[#This Row],[Fare correción 2]]/10,Tabla3[[#This Row],[Fare correción 2]]) -> 8.05 | B79: =IF(Tabla3[[#This Row],[Fare corrección]]>1000,Tabla3[[#This Row],[Fare corrección]]/1000,Tabla3[[#This Row],[Fare corrección]]) -> 8.05 | C79: =IF(ISNUMBER(Tabla3[[#This Row],[Fare]]),Tabla3[[#This Row],[Fare]],VALUE(SUBSTITUTE(Tabla3[[#This Row],[Fare]],".",","))) -> 8.05 | D79: 8.05
A80: =IF(Tabla3[[#This Row],[Fare correción 2]]>=1000,Tabla3[[#This Row],[Fare correción 2]]/10,Tabla3[[#This Row],[Fare correción 2]]) -> 29 | B80: =IF(Tabla3[[#This Row],[Fare corrección]]>1000,Tabla3[[#This Row],[Fare corrección]]/1000,Tabla3[[#This Row],[Fare corrección]]) -> 29 | C80: =IF(ISNUMBER(Tabla3[[#This Row],[Fare]]),Tabla3[[#This Row],[Fare]],VALUE(SUBSTITUTE(Tabla3[[#This Row],[Fare]],".",","))) -> 29 | D80: 29
A81: =IF(Tabla3[[#This Row],[Fare correción 2]]>=1000,Tabla3[[#This Row],[Fare correción 2]]/10,Tabla3[[#This Row],[Fare correción 2]]) -> 12.475 | B81: =IF(Tabla3[[#This Row],[Fare corrección]]>1000,Tabla3[[#This Row],[Fare corrección]]/1000,Tabla3[[#This Row],[Fare corrección]]) -> 12.475 | C81: =IF(ISNUMBER(Tabla3[[#This Row],[Fare]]),Tabla3[[#This Row],[Fare]],VALUE(SUBSTITUTE(Tabla3[[#This Row],[Fare]],".",","))) -> 12475 | D81: 12475
A82: =IF(Tabla3[[#This Row],[Fare correción 2]]>=1000,Tabla3[[#This Row],[Fare correción 2]]/10,Tabla3[[#This Row],[Fare correción 2]]) -> 9 | B82: =IF(Tabla3[[#This Row],[Fare corrección]]>1000,Tabla3[[#This Row],[Fare corrección]]/1000,Tabla3[[#This Row],[Fare corrección]]) -> 9 | C82: =IF(ISNUMBER(Tabla3[[#This Row],[Fare]]),Tabla3[[#This Row],[Fare]],VALUE(SUBSTITUTE(Tabla3[[#This Row],[Fare]],".",","))) -> 9 | D82: 9
A83: =IF(Tabla3[[#This Row],[Fare correción 2]]>=1000,Tabla3[[#This Row],[Fare correción 2]]/10,Tabla3[[#This Row],[Fare correción 2]]) -> 9.5 | B83: =IF(Tabla3[[#This Row],[Fare corrección]]>1000,Tabla3[[#This Row],[Fare corrección]]/1000,Tabla3[[#This Row],[Fare corrección]]) -> 9.5 | C83: =IF(ISNUMBER(Tabla3[[#This Row],[Fare]]),Tabla3[[#This Row],[Fare]],VALUE(SUBSTITUTE(Tabla3[[#This Row],[Fare]],".",","))) -> 9.5 | D83: 9.5
A84: =IF(Tabla3[[#This Row],[Fare correción 2]]>=1000,Tabla3[[#This Row],[Fare correción 2]]/10,Tabla3[[#This Row],[Fare correción 2]]) -> 77.875 | B84: =IF(Tabla3[[#This Row],[Fare corrección]]>1000,Tabla3[[#This Row],[Fare corrección]]/1000,Tabla3[[#This Row],[Fare corrección]]) -> 77.875 | C84: =IF(ISNUMBER(Tabla3[[#This Row],[Fare]]),Tabla3[[#This Row],[Fare]],VALUE(SUBSTITUTE(Tabla3[[#This Row],[Fare]],".",","))) -> 77875 | D84: 77875
A85: =IF(Tabla3[[#This Row],[Fare correción 2]]>=1000,Tabla3[[#This Row],[Fare correción 2]]/10,Tabla3[[#This Row],[Fare correción 2]]) -> 47.1 | B85: =IF(Tabla3[[#This Row],[Fare corrección]]>1000,Tabla3[[#This Row],[Fare corrección]]/1000,Tabla3[[#This Row],[Fare corrección]]) -> 47.1 | C85: =IF(ISNUMBER(Tabla3[[#This Row],[Fare]]),Tabla3[[#This Row],[Fare]],VALUE(SUBSTITUTE(Tabla3[[#This Row],[Fare]],".",","))) -> 47.1 | D85: 47.1
A86: =IF(Tabla3[[#This Row],[Fare correción 2]]>=1000,Tabla3[[#This Row],[Fare correción 2]]/10,Tabla3[[#This Row],[Fare correción 2]]) -> 10.5 | B86: =IF(Tabla3[[#This Row],[Fare corrección]]>1000,Tabla3[[#This Row],[Fare corrección]]/1000,Tabla3[[#This Row],[Fare corrección]]) -> 10.5 | C86: =IF(ISNUMBER(Tabla3[[#This Row],[Fare]]),Tabla3[[#This Row],[Fare]],VALUE(SUBSTITUTE(Tabla3[[#This Row],[Fare]],".",","))) -> 10.5 | D86: 10.5
A87: =IF(Tabla3[[#This Row],[Fare correción 2]]>=1000,Tabla3[[#This Row],[Fare correción 2]]/10,Tabla3[[#This Row],[Fare correción 2]]) -> 15.85 | B87: =IF(Tabla3[[#This Row],[Fare corrección]]>1000,Tabla3[[#This Row],[Fare corrección]]/1000,Tabla3[[#This Row],[Fare corrección]]) -> 15.85 | C87: =IF(ISNUMBER(Tabla3[[#This Row],[Fare]]),Tabla3[[#This Row],[Fare]],VALUE(SUBSTITUTE(Tabla3[[#This Row],[Fare]],".",","))) -> 15.85 | D87: 15.85
A88: =IF(Tabla3[[#This Row],[Fare correción 2]]>=1000,Tabla3[[#This Row],[Fare correción 2]]/10,Tabla3[[#This Row],[Fare correción 2]]) -> 34.375 | B88: =IF(Tabla3[[#This Row],[Fare corrección]]>1000,Tabla3[[#This Row],[Fare corrección]]/1000,Tabla3[[#This Row],[Fare corrección]]) -> 34.375 | C88: =IF(ISNUMBER(Tabla3[[#This Row],[Fare]]),Tabla3[[#This Row],[Fare]],VALUE(SUBSTITUTE(Tabla3[[#This Row],[Fare]],".",","))) -> 34375 | D88: 34375
A89: =IF(Tabla3[[#This Row],[Fare correción 2]]>=1000,Tabla3[[#This Row],[Fare correción 2]]/10,Tabla3[[#This Row],[Fare correción 2]]) -> 8.05 | B89: =IF(Tabla3[[#This Row],[Fare corrección]]>1000,Tabla3[[#This Row],[Fare corrección]]/1000,Tabla3[[#This Row],[Fare corrección]]) -> 8.05 | C89: =IF(ISNUMBER(Tabla3[[#This Row],[Fare]]),Tabla3[[#This Row],[Fare]],VALUE(SUBSTITUTE(Tabla3[[#This Row],[Fare]],".",","))) -> 8.05 | D89: 8.05
A90: =IF(Tabla3[[#This Row],[Fare correción 2]]>=1000,Tabla3[[#This Row],[Fare correción 2]]/10,Tabla3[[#This Row],[Fare correción 2]]) -> 263 | B90: =IF(Tabla3[[#This Row],[Fare corrección]]>1000,Tabla3[[#This Row],[Fare corrección]]/1000,Tabla3[[#This Row],[Fare corrección]]) -> 263 | C90: =IF(ISNUMBER(Tabla3[[#This Row],[Fare]]),Tabla3[[#This Row],[Fare]],VALUE(SUBSTITUTE(Tabla3[[#This Row],[Fare]],".",","))) -> 263 | D90: 263
A91: =IF(Tabla3[[#This Row],[Fare correción 2]]>=1000,Tabla3[[#This Row],[Fare correción 2]]/10,Tabla3[[#This Row],[Fare correción 2]]) -> 8.05 | B91: =IF(Tabla3[[#This Row],[Fare corrección]]>1000,Tabla3[[#This Row],[Fare corrección]]/1000,Tabla3[[#This Row],[Fare corrección]]) -> 8.05 | C91: =IF(ISNUMBER(Tabla3[[#This Row],[Fare]]),Tabla3[[#This Row],[Fare]],VALUE(SUBSTITUTE(Tabla3[[#This Row],[Fare]],".",","))) -> 8.05 | D91: 8.05
A92: =IF(Tabla3[[#This Row],[Fare correción 2]]>=1000,Tabla3[[#This Row],[Fare correción 2]]/10,Tabla3[[#This Row],[Fare correción 2]]) -> 8.05 | B92: =IF(Tabla3[[#This Row],[Fare corrección]]>1000,Tabla3[[#This Row],[Fare corrección]]/1000,Tabla3[[#This Row],[Fare corrección]]) -> 8.05 | C92: =IF(ISNUMBER(Tabla3[[#This Row],[Fare]]),Tabla3[[#This Row],[Fare]],VALUE(SUBSTITUTE(Tabla3[[#This Row],[Fare]],".",","))) -> 8.05 | D92: 8.05
A93: =IF(Tabla3[[#This Row],[Fare correción 2]]>=1000,Tabla3[[#This Row],[Fare correción 2]]/10,Tabla3[[#This Row],[Fare correción 2]]) -> 78.542 | B93: =IF(Tabla3[[#This Row],[Fare corrección]]>1000,Tabla3[[#This Row],[Fare corrección]]/1000,Tabla3[[#This Row],[Fare corrección]]) -> 78.542 | C93: =IF(ISNUMBER(Tabla3[[#This Row],[Fare]]),Tabla3[[#This Row],[Fare]],VALUE(SUBSTITUTE(Tabla3[[#This Row],[Fare]],".",","))) -> 78542 | D93: 78542
A94: =IF(Tabla3[[#This Row],[Fare correción 2]]>=1000,Tabla3[[#This Row],[Fare correción 2]]/10,Tabla3[[#This Row],[Fare correción 2]]) -> 61.175 | B94: =IF(Tabla3[[#This Row],[Fare corrección]]>1000,Tabla3[[#This Row],[Fare corrección]]/1000,Tabla3[[#This Row],[Fare corrección]]) -> 61.175 | C94: =IF(ISNUMBER(Tabla3[[#This Row],[Fare]]),Tabla3[[#This Row],[Fare]],VALUE(SUBSTITUTE(Tabla3[[#This Row],[Fare]],".",","))) -> 61175 | D94: 61175
A95: =IF(Tabla3[[#This Row],[Fare correción 2]]>=1000,Tabla3[[#This Row],[Fare correción 2]]/10,Tabla3[[#This Row],[Fare correción 2]]) -> 20.575 | B95: =IF(Tabla3[[#This Row],[Fare corrección]]>1000,Tabla3[[#This Row],[Fare corrección]]/1000,Tabla3[[#This Row],[Fare corrección]]) -> 20.575 | C95: =IF(ISNUMBER(Tabla3[[#This Row],[Fare]]),Tabla3[[#This Row],[Fare]],VALUE(SUBSTITUTE(Tabla3[[#This Row],[Fare]],".",","))) -> 20575 | D95: 20575
A96: =IF(Tabla3[[#This Row],[Fare correción 2]]>=1000,Tabla3[[#This Row],[Fare correción 2]]/10,Tabla3[[#This Row],[Fare correción 2]]) -> 7.25 | B96: =IF(Tabla3[[#This Row],[Fare corrección]]>1000,Tabla3[[#This Row],[Fare corrección]]/1000,Tabla3[[#This Row],[Fare corrección]]) -> 7.25 | C96: =IF(ISNUMBER(Tabla3[[#This Row],[Fare]]),Tabla3[[#This Row],[Fare]],VALUE(SUBSTITUTE(Tabla3[[#This Row],[Fare]],".",","))) -> 7.25 | D96: 7.25
A97: =IF(Tabla3[[#This Row],[Fare correción 2]]>=1000,Tabla3[[#This Row],[Fare correción 2]]/10,Tabla3[[#This Row],[Fare correción 2]]) -> 8.05 | B97: =IF(Tabla3[[#This Row],[Fare corrección]]>1000,Tabla3[[#This Row],[Fare corrección]]/1000,Tabla3[[#This Row],[Fare corrección]]) -> 8.05 | C97: =IF(ISNUMBER(Tabla3[[#This Row],[Fare]]),Tabla3[[#This Row],[Fare]],VALUE(SUBSTITUTE(Tabla3[[#This Row],[Fare]],".",","))) -> 8.05 | D97: 8.05
A98: =IF(Tabla3[[#This Row],[Fare correción 2]]>=1000,Tabla3[[#This Row],[Fare correción 2]]/10,Tabla3[[#This Row],[Fare correción 2]]) -> 346.542 | B98: =IF(Tabla3[[#This Row],[Fare corrección]]>1000,Tabla3[[#This Row],[Fare corrección]]/1000,Tabla3[[#This Row],[Fare corrección]]) -> 346.542 | C98: =IF(ISNUMBER(Tabla3[[#This Row],[Fare]]),Tabla3[[#This Row],[Fare]],VALUE(SUBSTITUTE(Tabla3[[#This Row],[Fare]],".",","))) -> 346542 | D98: 346542
A99: =IF(Tabla3[[#This Row],[Fare correción 2]]>=1000,Tabla3[[#This Row],[Fare correción 2]]/10,Tabla3[[#This Row],[Fare correción 2]]) -> 633.583 | B99: =IF(Tabla3[[#This Row],[Fare corrección]]>1000,Tabla3[[#This Row],[Fare corrección]]/1000,Tabla3[[#This Row],[Fare corrección]]) -> 633.583 | C99: =IF(ISNUMBER(Tabla3[[#This Row],[Fare]]),Tabla3[[#This Row],[Fare]],VALUE(SUBSTITUTE(Tabla3[[#This Row],[Fare]],".",","))) -> 633583 | D99: 633583
A100: =IF(Tabla3[[#This Row],[Fare correción 2]]>=1000,Tabla3[[#This Row],[Fare correción 2]]/10,Tabla3[[#This Row],[Fare correción 2]]) -> 23 | B100: =IF(Tabla3[[#This Row],[Fare corrección]]>1000,Tabla3[[#This Row],[Fare corrección]]/1000,Tabla3[[#This Row],[Fare corrección]]) -> 23 | C100: =IF(ISNUMBER(Tabla3[[#This Row],[Fare]]),Tabla3[[#This Row],[Fare]],VALUE(SUBSTITUTE(Tabla3[[#This Row],[Fare]],".",","))) -> 23 | D100: 23
...

Sheet DASHBOARD
N3: ANÁLISIS DE SUPERVIVENCIA — TITANIC
N5: Resumen estadistico de pasajeros y tasas de supervivencia
M7: TOTAL DE PASAJEROS | N7: TOTAL SOBREVIVIENTES | O7: TASA DE SUPERVIVENCIA
M8: =AUXILIAR!D4 -> 891 | N8: =GETPIVOTDATA("Sobreviviente",AUXILIAR!$E$3) -> 109 | O8: =N8/M8 -> 0.12233446
M9: TOTAL HOMBRES | N9: HOMBRES SOBREVIVIENTES | O9: TASA DE SUP HOMBRES
M10: =AUXILIAR!D5 -> 577 | N10: =AUXILIAR!E5 -> 109 | O10: =N10/M10 -> 0.18890815
M11: TOTAL MUJERES | N11: MUJERES SOBREVIVIENTES | O11: TASA DE SUP MUJERES
M12: =AUXILIAR!D6 -> 314 | N12: =AUXILIAR!E6 -> 233 | O12: =N12/M12 -> 0.74203822
C35: Dashboard interactivo con segmentación dinámica y análisis multivariable
